{
  "questions": [
    {
      "question": "Qual é o primeiro passo na classificação GINA de gravidade da asma?",
      "options": [
        "Identifique o nível de controle",
        "Medir o óxido nítrico exalado",
        "Avalie a função pulmonar",
        "Realizar teste de broncoprovocação"
      ],
      "correctAnswer": 1,
      "explanation": "A classificação de gravidade da GINA baseia-se inicialmente no nível de controle dos sintomas e no risco de exacerbações, e não em testes de função pulmonar ou biomarcadores.",
      "hashtags": [
        "pneumologia",
        "asma",
        "conceito",
        "gina_classificação",
        "MEDICAL_TOPIC",
        "GINA 2023"
      ]
    },
    {
      "question": "O que define asma leve de acordo com a classificação GINA?",
      "options": [
        "Sintomas diários e despertares noturnos",
        "Sintomas menos de duas vezes por semana",
        "VEF1 inferior a 60% do previsto",
        "Exacerbações graves recorrentes"
      ],
      "correctAnswer": 2,
      "explanation": "A asma leve segundo GINA é caracterizada por sintomas diurnos menos de duas vezes por semana, sem despertares noturnos ou limitação de atividades, com função pulmonar normal.",
      "hashtags": [
        "pneumologia",
        "asma",
        "tabela_clínica",
        "asma_leve",
        "MEDICAL_TOPIC",
        "GINA 2023"
      ]
    },
    {
      "question": "Qual é o tratamento de manutenção recomendado para asma moderada na GINA?",
      "options": [
        "Corticosteroides orais diários",
        "Somente SABA sob demanda",
        "Corticosteróides inalados em doses baixas",
        "Corticosteróides inalados em doses médias"
      ],
      "correctAnswer": 4,
      "explanation": "Para asma moderada, a GINA recomenda corticosteroides inalatórios em doses médias como terapia de manutenção, reservando doses altas ou orais para casos mais graves.",
      "hashtags": [
        "pneumologia",
        "asma",
        "tratamento",
        "corticosteróides inalados",
        "MEDICAL_TOPIC",
        "GINA 2023"
      ]
    },
    {
      "question": "Qual parâmetro indica asma grave não controlada de acordo com a GINA?",
      "options": [
        "Exacerbações que requerem corticosteróides orais",
        "98% de saturação de oxigênio",
        "Usar SABA mais de duas vezes por mês",
        "VEF1 maior que 90% do previsto"
      ],
      "correctAnswer": 1,
      "explanation": "A asma grave não controlada é definida por exacerbações frequentes que requerem corticosteróides orais, apesar do tratamento ideal com altas doses de corticosteróides inalados.",
      "hashtags": [
        "pneumologia",
        "asma",
        "tabela_clínica",
        "asma_grave",
        "MEDICAL_TOPIC",
        "GINA 2023"
      ]
    },
    {
      "question": "Quantas etapas de tratamento tem a classificação GINA para asma?",
      "options": [
        "Quatro etapas",
        "três etapas",
        "Cinco etapas",
        "seis passos"
      ],
      "correctAnswer": 3,
      "explanation": "A classificação GINA do tratamento da asma consiste em cinco etapas, desde a etapa 1 (asma leve) até a etapa 5 (asma grave), ajustando a intensidade terapêutica.",
      "hashtags": [
        "pneumologia",
        "asma",
        "conceito",
        "passos_gina",
        "MEDICAL_TOPIC",
        "GINA 2023"
      ]
    },
    {
      "question": "Qual medicamento é adicionado na etapa 5 do GINA para asma grave?",
      "options": [
        "teofilina oral",
        "Antagonistas de leucotrienos",
        "fenoterol inalado",
        "Corticosteróides inalados em altas doses"
      ],
      "correctAnswer": 4,
      "explanation": "Na etapa 5 da GINA, são adicionados corticosteroides inalatórios em altas doses como terapia de manutenção, juntamente com outras opções, como anticolinérgicos ou biológicos.",
      "hashtags": [
        "pneumologia",
        "asma",
        "tratamento",
        "etapa_5",
        "MEDICAL_TOPIC",
        "GINA 2023"
      ]
    },
    {
      "question": "Qual é a tríade clássica dos sintomas da asma?",
      "options": [
        "Dispneia, chiado no peito, tosse",
        "Febre, dor no peito, tosse",
        "Hemoptise, dispneia, cianose",
        "Estertores, febre, expectoração"
      ],
      "correctAnswer": 1,
      "explanation": "A tríade clássica da asma inclui dispneia (falta de ar), chiado no peito (assobio ao expirar) e tosse, muitas vezes à noite ou com exercícios.",
      "hashtags": [
        "pneumologia",
        "asma",
        "tabela_clínica",
        "tríade_sintomática",
        "MEDICAL_TOPIC",
        "GINA 2023"
      ]
    },
    {
      "question": "Qual sintoma da asma costuma piorar à noite ou ao amanhecer?",
      "options": [
        "Chiado",
        "Aperto no peito",
        "Dispneia",
        "Tosse"
      ],
      "correctAnswer": 4,
      "explanation": "A tosse na asma é caracteristicamente noturna ou matinal, muitas vezes o primeiro sintoma a aparecer e um marcador de mau controle.",
      "hashtags": [
        "pneumologia",
        "asma",
        "tabela_clínica",
        "sintoma_noturno",
        "MEDICAL_TOPIC",
        "GINA 2023"
      ]
    },
    {
      "question": "Qual das alternativas a seguir é um sintoma típico de asma em crianças?",
      "options": [
        "Chiado recorrente",
        "Dispneia aos esforços",
        "Cianose perioral",
        "dor abdominal"
      ],
      "correctAnswer": 1,
      "explanation": "A sibilância recorrente é o sintoma principal da asma infantil, muitas vezes desencadeada por infecções virais ou alérgenos.",
      "hashtags": [
        "pediatria",
        "infância_asma",
        "tabela_clínica",
        "chiados_recorrentes",
        "MEDICAL_TOPIC",
        "GINA 2023"
      ]
    },
    {
      "question": "Que característica distingue a dispneia asmática da dispneia da DPOC?",
      "options": [
        "Dispneia progressiva",
        "Dispneia com febre alta",
        "Dispnéia com tosse úmida",
        "Dispneia de início agudo"
      ],
      "correctAnswer": 4,
      "explanation": "A dispneia asmática é geralmente de início agudo, episódica e reversível, ao contrário da dispneia progressiva e crônica da DPOC.",
      "hashtags": [
        "pneumologia",
        "asma_vs_epoc",
        "tabela_clínica",
        "dispnéia_aguda",
        "MEDICAL_TOPIC",
        "Harrison 21 anos"
      ]
    },
    {
      "question": "Qual dos seguintes sintomas é mais específico da asma aguda grave?",
      "options": [
        "Leve aperto no peito",
        "Tosse seca",
        "Incapacidade de falar",
        "Chiado audível"
      ],
      "correctAnswer": 3,
      "explanation": "A incapacidade de falar devido à dispneia grave é um sinal de asma aguda grave, indicando obstrução crítica e necessidade de atendimento urgente.",
      "hashtags": [
        "pneumologia",
        "asma_aguda",
        "tabela_clínica",
        "asma_severidade",
        "MEDICAL_TOPIC",
        "GINA 2023"
      ]
    },
    {
      "question": "Que sintoma de asma pode persistir entre as exacerbações?",
      "options": [
        "Aperto no peito",
        "Dispneia em repouso",
        "Tosse crônica",
        "Chiado contínuo"
      ],
      "correctAnswer": 3,
      "explanation": "A tosse crônica, muitas vezes seca ou com pouca expectoração, pode ser o único sintoma persistente entre as crises de asma, especialmente na variante tosse da asma.",
      "hashtags": [
        "pneumologia",
        "asma",
        "tabela_clínica",
        "tosse_crônica",
        "MEDICAL_TOPIC",
        "Harrison 21 anos"
      ]
    },
    {
      "question": "Qual dos seguintes achados é mais característico da asma do que da DPOC?",
      "options": [
        "Obstrução reversível do fluxo de ar",
        "Dispneia progressiva aos esforços",
        "Tosse matinal produtiva",
        "Diminuição da capacidade de difusão"
      ],
      "correctAnswer": 1,
      "explanation": "A obstrução reversível do fluxo aéreo é uma marca registrada da asma, enquanto na DPOC a obstrução é tipicamente irreversível ou apenas parcialmente reversível.",
      "hashtags": [
        "pneumologia",
        "asma_epoc",
        "diagnóstico",
        "obstrução_reversibilidade",
        "MEDICAL_TOPIC",
        "GINA 2023 --- OURO 2023"
      ]
    },
    {
      "question": "Qual característica clínica é mais sugestiva de asma do que DPOC em um idoso?",
      "options": [
        "Sintomas variáveis ​​e gatilhos alérgicos",
        "Cor pulmonale em estágio avançado",
        "Início dos sintomas após 40 anos",
        "História de tabagismo de 30 maços-ano"
      ],
      "correctAnswer": 1,
      "explanation": "A asma é caracterizada por sintomas variáveis, muitas vezes desencadeados por alérgenos, enquanto a DPOC está associada ao tabagismo e a sintomas mais persistentes e progressivos.",
      "hashtags": [
        "pneumologia",
        "asma_epoc",
        "tabela_clínica",
        "sintomas_variáveis",
        "MEDICAL_TOPIC",
        "GINA 2023"
      ]
    },
    {
      "question": "Qual teste de função pulmonar é mais útil para diferenciar asma da DPOC?",
      "options": [
        "Pressão inspiratória máxima",
        "Capacidade pulmonar total",
        "Teste de reversibilidade do broncodilatador",
        "Volume residual"
      ],
      "correctAnswer": 3,
      "explanation": "O teste de reversibilidade do broncodilatador avalia o aumento do VEF1 após a inalação de um broncodilatador; um aumento significativo é típico da asma e raro na DPOC.",
      "hashtags": [
        "pneumologia",
        "asma_epoc",
        "diagnóstico",
        "teste_de reversibilidade",
        "MEDICAL_TOPIC",
        "OURO 2023"
      ]
    },
    {
      "question": "Qual dos seguintes parâmetros espirométricos é fundamental para confirmar a DPOC em vez da asma?",
      "options": [
        "Diminuição do pico de fluxo expiratório",
        "VEF1/CVF > 0,85 pós-broncodilatador",
        "Aumento do VEF1 > 12% e 200 mL",
        "VEF1/CVF < 0,70 pós-broncodilatador"
      ],
      "correctAnswer": 4,
      "explanation": "Uma relação VEF1/CVF < 0,70 pós-broncodilatador indica obstrução persistente, característica da DPOC, enquanto na asma a obstrução é geralmente reversível.",
      "hashtags": [
        "pneumologia",
        "asma_epoc",
        "diagnóstico",
        "espirometria",
        "MEDICAL_TOPIC",
        "OURO 2023"
      ]
    },
    {
      "question": "Qual biomarcador inflamatório está tipicamente associado à asma eosinofílica?",
      "options": [
        "procalcitonina elevada",
        "Proteína C reativa elevada",
        "Neutrófilos elevados no escarro",
        "Eosinófilos elevados no escarro"
      ],
      "correctAnswer": 4,
      "explanation": "A asma eosinofílica é caracterizada por eosinófilos elevados no escarro, enquanto a DPOC geralmente apresenta inflamação neutrofílica, embora possa haver fenótipos mistos.",
      "hashtags": [
        "pneumologia",
        "asma_epoc",
        "diagnóstico",
        "expectoração_eosinófilos",
        "MEDICAL_TOPIC",
        "GINA 2023"
      ]
    },
    {
      "question": "Qual dos seguintes antecedentes apoia mais o diagnóstico de DPOC do que asma?",
      "options": [
        "Fumar mais de 20 maços-ano",
        "História de rinite alérgica",
        "Sintomas desde a infância",
        "Exposição ocupacional a alérgenos"
      ],
      "correctAnswer": 1,
      "explanation": "O tabagismo significativo (>20 maços-ano) é o principal fator de risco para DPOC, enquanto a asma está mais associada à atopia e aos sintomas desde a infância.",
      "hashtags": [
        "pneumologia",
        "asma_epoc",
        "etiologia",
        "fumar",
        "MEDICAL_TOPIC",
        "OURO 2023"
      ]
    },
    {
      "question": "Qual critério funcional define um teste broncodilatador positivo em adultos?",
      "options": [
        "Diminuição do VEF1 ≥ 15%",
        "Aumento do VEF1 ≥ 12% e ≥ 200 ml",
        "Aumento do VEF1 ≥ 10% e ≥ 150 ml",
        "Aumento do PFE ≥ 20%"
      ],
      "correctAnswer": 2,
      "explanation": "Um teste broncodilatador positivo é definido como um aumento no VEF1 ≥ 12% e ≥ 200 ml em relação ao valor basal após a administração de um broncodilatador de ação curta, indicando reversibilidade da obstrução.",
      "hashtags": [
        "pneumologia",
        "teste_broncodilatador_positivo",
        "diagnóstico",
        "critérios_funcionais",
        "MEDICAL_TOPIC",
        "GEMA 2024"
      ]
    },
    {
      "question": "Qual medicamento é normalmente usado para realizar o teste broncodilatador?",
      "options": [
        "salbutamol inalado",
        "Prednisona oral",
        "Teofilina intravenosa",
        "Montelucaste oral"
      ],
      "correctAnswer": 1,
      "explanation": "O salbutamol inalatório é o broncodilatador de curta ação de escolha para a prova broncodilatadora, administrando 200-400 µg, com avaliação espirométrica após 15-20 minutos.",
      "hashtags": [
        "pneumologia",
        "teste_broncodilatador_positivo",
        "tratamento",
        "broncodilatadores",
        "MEDICAL_TOPIC",
        "GEMA 2024"
      ]
    },
    {
      "question": "Qual é a principal utilidade clínica de um teste broncodilatador positivo?",
      "options": [
        "Confirmar o diagnóstico de asma",
        "Descartar doença pulmonar restritiva",
        "Avaliar a capacidade de difusão pulmonar",
        "Identificar hipertensão pulmonar"
      ],
      "correctAnswer": 1,
      "explanation": "Um teste broncodilatador positivo indica reversibilidade da obstrução ao fluxo aéreo, que é um critério diagnóstico fundamental para asma, diferenciando-a de outras doenças obstrutivas crônicas.",
      "hashtags": [
        "pneumologia",
        "teste_broncodilatador_positivo",
        "diagnóstico",
        "interpretação_clínica",
        "MEDICAL_TOPIC",
        "GEMA 2024"
      ]
    },
    {
      "question": "Qual parâmetro espirométrico é avaliado principalmente no teste broncodilatador?",
      "options": [
        "Capacidade vital forçada (CVF)",
        "Pico de Fluxo Expiratório (PFE)",
        "Capacidade pulmonar total (CPT)",
        "Volume expiratório forçado em 1 segundo (VEF1)"
      ],
      "correctAnswer": 4,
      "explanation": "O VEF1 é o principal parâmetro para avaliar a reversibilidade brônquica, pois mede o volume de ar expirado no primeiro segundo, sendo sensível às alterações induzidas pelos broncodilatadores.",
      "hashtags": [
        "pneumologia",
        "teste_broncodilatador_positivo",
        "diagnóstico",
        "espirometria",
        "MEDICAL_TOPIC",
        "GEMA 2024"
      ]
    },
    {
      "question": "Em que patologia o teste broncodilatador costuma ser negativo?",
      "options": [
        "Asma leve intermitente",
        "Fibrose pulmonar idiopática",
        "DPOC avançada",
        "displasia broncopulmonar"
      ],
      "correctAnswer": 2,
      "explanation": "A fibrose pulmonar idiopática é uma doença pulmonar restritiva e não obstrutiva, portanto o teste broncodilatador não mostra reversibilidade significativa, ao contrário da asma ou da DPOC.",
      "hashtags": [
        "pneumologia",
        "teste_broncodilatador_positivo",
        "diagnóstico_diferencial",
        "doença_restritiva",
        "MEDICAL_TOPIC",
        "GEMA 2024"
      ]
    },
    {
      "question": "Quanto tempo devo esperar após a inalação do broncodilatador para repetir a espirometria?",
      "options": [
        "2 horas",
        "5 minutos",
        "45-60 minutos",
        "15-20 minutos"
      ],
      "correctAnswer": 4,
      "explanation": "Após a administração de um broncodilatador de curta ação como o salbutamol, recomenda-se esperar 15-20 minutos para repetir a espirometria, tempo suficiente para atingir o efeito broncodilatador máximo.",
      "hashtags": [
        "pneumologia",
        "teste_broncodilatador_positivo",
        "diagnóstico",
        "procedimento_técnico",
        "MEDICAL_TOPIC",
        "GEMA 2024"
      ]
    },
    {
      "question": "Qual parâmetro mede o pico de fluxo expiratório (PFE)?",
      "options": [
        "Pico de fluxo expiratório",
        "Capacidade pulmonar total",
        "Pressão arterial de oxigênio",
        "Volume expiratório forçado"
      ],
      "correctAnswer": 1,
      "explanation": "O pico de fluxo expiratório mede o fluxo máximo alcançado durante a expiração forçada, refletindo a obstrução das grandes vias aéreas.",
      "hashtags": [
        "pneumologia",
        "asma",
        "conceito",
        "pico_expiratório_fluxo",
        "MEDICAL_TOPIC",
        ""
      ]
    },
    {
      "question": "Quando a variabilidade do PFE é considerada anormal na asma?",
      "options": [
        "Variação > 50% em 24 horas",
        "Variação > 20% em 3 dias",
        "Variação < 10% em 1 semana",
        "Variação < 5% em 1 mês"
      ],
      "correctAnswer": 2,
      "explanation": "Uma variabilidade do PFE superior a 20% em pelo menos 3 dias durante 2 semanas é um critério diagnóstico para asma, indicando obstrução reversível.",
      "hashtags": [
        "pneumologia",
        "asma",
        "diagnóstico",
        "variabilidade_pfe",
        "MEDICAL_TOPIC",
        ""
      ]
    },
    {
      "question": "Qual fator pode reduzir a precisão do PFE?",
      "options": [
        "Descanse por 10 minutos antes",
        "Medição na posição sentada",
        "Esforço submáximo do paciente",
        "Uso prévio de broncodilatadores"
      ],
      "correctAnswer": 3,
      "explanation": "O uso de broncodilatadores antes da medição pode mascarar a obstrução basal, reduzindo a precisão do PFE para avaliar o controle da asma.",
      "hashtags": [
        "pneumologia",
        "asma",
        "tratamento",
        "broncodilatadores",
        "MEDICAL_TOPIC",
        ""
      ]
    },
    {
      "question": "Qual é o principal uso do PFE na asma?",
      "options": [
        "Detectar hiperinflação",
        "Avaliar obstrução reversível",
        "Diagnosticar fibrose pulmonar",
        "Medir a capacidade de difusão"
      ],
      "correctAnswer": 2,
      "explanation": "O PFE é usado principalmente para monitorar a obstrução reversível das vias aéreas na asma, ajudando a avaliar o controle e a resposta ao tratamento.",
      "hashtags": [
        "pneumologia",
        "asma",
        "fisiopatologia",
        "obstrução_reversível",
        "MEDICAL_TOPIC",
        ""
      ]
    },
    {
      "question": "Qual valor de PFE sugere uma exacerbação grave da asma?",
      "options": [
        "Mais de 80% do previsto",
        "Menos de 50% do previsto",
        "Entre 60% e 70% do previsto",
        "Entre 90% e 100% do previsto"
      ],
      "correctAnswer": 2,
      "explanation": "Um PFE inferior a 50% do valor previsto indica uma exacerbação grave da asma, necessitando de intervenção médica urgente de acordo com as diretrizes clínicas.",
      "hashtags": [
        "pneumologia",
        "asma",
        "tabela_clínica",
        "exacerbação_grave",
        "MEDICAL_TOPIC",
        ""
      ]
    },
    {
      "question": "Como se expressa a variabilidade do PFE no diagnóstico de asma?",
      "options": [
        "Desvio padrão semanal",
        "Relação com CVF",
        "Diferença absoluta em L/min",
        "Porcentagem do valor médio"
      ],
      "correctAnswer": 4,
      "explanation": "A variabilidade do PFE é expressa como o percentual do valor médio diário, calculando-se a diferença entre o máximo e o mínimo dividida pela média.",
      "hashtags": [
        "pneumologia",
        "asma",
        "diagnóstico",
        "porcentagem_variabilidade",
        "MEDICAL_TOPIC",
        ""
      ]
    },
    {
      "question": "Qual é o primeiro passo no tratamento de manutenção da asma em adultos?",
      "options": [
        "LABA isolado",
        "GCS inalado em baixa dose",
        "SABA sob demanda",
        "Montelucaste oral"
      ],
      "correctAnswer": 3,
      "explanation": "O primeiro passo do tratamento de manutenção da asma em adultos consiste no uso de SABA conforme a necessidade, sem a necessidade de corticosteróide inalatório diário em pacientes com asma intermitente.",
      "hashtags": [
        "pneumologia",
        "asma_brônquica",
        "tratamento",
        "primeiro_passo",
        "MEDICAL_TOPIC",
        "GINA 2023"
      ]
    },
    {
      "question": "Qual medicamento é adicionado na etapa 3 do tratamento da asma?",
      "options": [
        "tiotrópio inalado",
        "Prednisona oral",
        "Budesonida/formoterol",
        "Formoterol sozinho"
      ],
      "correctAnswer": 3,
      "explanation": "Na etapa 3 da terapia da asma, recomenda-se um corticosteroide inalado em dose baixa combinado com formoterol para uso de manutenção e alívio (MART).",
      "hashtags": [
        "pneumologia",
        "asma_brônquica",
        "tratamento",
        "etapa_3",
        "MEDICAL_TOPIC",
        "GINA 2023"
      ]
    },
    {
      "question": "Qual é o próximo passo quando a asma não é controlada com meia dose de GCS inalado mais LABA?",
      "options": [
        "Aumento para altas doses de GCS",
        "Adicionar montelucaste oral",
        "Iniciar anti-IgE",
        "Suspender LABA"
      ],
      "correctAnswer": 1,
      "explanation": "Quando a asma não é controlada com GCS inalados em doses médias mais LABA, o passo 4 recomenda aumentar os GCS inalados em altas doses enquanto se mantém o LABA, antes de adicionar terapias biológicas.",
      "hashtags": [
        "pneumologia",
        "asma_brônquica",
        "tratamento",
        "etapa_4",
        "MEDICAL_TOPIC",
        "GINA 2023"
      ]
    },
    {
      "question": "Qual opção é correta para a asma grave do passo 5?",
      "options": [
        "Corticosteróides inalados sozinhos",
        "Omalizumabe subcutâneo",
        "teofilina oral diária",
        "metotrexato semanal"
      ],
      "correctAnswer": 2,
      "explanation": "No estágio 5 da asma grave, recomenda-se a adição de um anticorpo monoclonal como o omalizumabe (anti-IgE) ou o mepolizumabe, voltado para fenótipos específicos de asma grave.",
      "hashtags": [
        "pneumologia",
        "asma_brônquica",
        "tratamento",
        "etapa_5",
        "MEDICAL_TOPIC",
        "GINA 2023"
      ]
    },
    {
      "question": "O que deve ser avaliado antes de passar para a próxima etapa terapêutica da asma?",
      "options": [
        "Volume expiratório forçado",
        "Teste de metacolina",
        "Nível sérico de IgE",
        "Adesão ao tratamento"
      ],
      "correctAnswer": 4,
      "explanation": "Antes de aumentar a etapa terapêutica na asma, deve-se avaliar a adesão ao tratamento e à técnica inalatória, pois o descontrole geralmente se deve à má adesão.",
      "hashtags": [
        "pneumologia",
        "asma_brônquica",
        "tratamento",
        "avaliação_anterior",
        "MEDICAL_TOPIC",
        "GINA 2023"
      ]
    },
    {
      "question": "Em que nível é considerada a adição de tiotrópio como terapia de manutenção?",
      "options": [
        "Etapa 5",
        "Etapa 2",
        "Etapa 3",
        "Etapa 4"
      ],
      "correctAnswer": 4,
      "explanation": "O tiotrópio inalado é adicionado como terapia de manutenção na asma passo 4, quando o controle não é alcançado com doses médias de GCS inalado mais LABA.",
      "hashtags": [
        "pneumologia",
        "asma_brônquica",
        "tratamento",
        "tiotrópio",
        "MEDICAL_TOPIC",
        "GINA 2023"
      ]
    },
    {
      "question": "Qual é o principal efeito dos corticosteróides inalados na asma?",
      "options": [
        "Redução da inflamação",
        "Eliminação de muco",
        "Broncodilatação imediata",
        "bloqueio de histamina"
      ],
      "correctAnswer": 1,
      "explanation": "Os corticosteróides inalatórios atuam principalmente reduzindo a inflamação das vias aéreas, inibindo a síntese de citocinas pró-inflamatórias e a migração de eosinófilos, controlando assim a hiper-reatividade brônquica.",
      "hashtags": [
        "pneumologia",
        "asma",
        "tratamento",
        "corticosteróides inalados",
        "MEDICAL_TOPIC",
        "GEMA 5.2"
      ]
    },
    {
      "question": "Qual medicamento é um corticosteróide inalado comumente usado na asma?",
      "options": [
        "Montelucaste",
        "Teofilina",
        "Salbutamol",
        "Budesonida"
      ],
      "correctAnswer": 4,
      "explanation": "A budesonida é um corticosteróide inalatório amplamente utilizado como tratamento de controle da asma persistente, reduzindo a inflamação brônquica e prevenindo exacerbações.",
      "hashtags": [
        "pneumologia",
        "asma",
        "farmacologia",
        "budesonida",
        "MEDICAL_TOPIC",
        "GINA 2023"
      ]
    },
    {
      "question": "Qual é um efeito adverso local comum do uso prolongado de corticosteróides inalados?",
      "options": [
        "Osteoporose grave",
        "Candidíase orofaríngea",
        "Insuficiência adrenal",
        "Pressão alta"
      ],
      "correctAnswer": 2,
      "explanation": "A candidíase orofaríngea é um efeito adverso local comum dos corticosteróides inalatórios, devido à deposição do medicamento na mucosa oral, evitável com enxaguatório bucal pós-inalatório.",
      "hashtags": [
        "pneumologia",
        "asma",
        "efeitos_adversos",
        "candidíase oral",
        "MEDICAL_TOPIC",
        "GEMA 5.2"
      ]
    },
    {
      "question": "Em que fase do tratamento da asma é recomendado iniciar corticosteróides inalatórios em adultos?",
      "options": [
        "Etapa 3",
        "Passo 1",
        "Etapa 4",
        "Etapa 2"
      ],
      "correctAnswer": 4,
      "explanation": "De acordo com as diretrizes da GINA, os corticosteróides inalados são introduzidos na etapa 2 como tratamento de controle de primeira linha para asma persistente leve, quando os sintomas não são controlados apenas com SABA.",
      "hashtags": [
        "pneumologia",
        "asma",
        "tratamento",
        "passo_terapêutico",
        "MEDICAL_TOPIC",
        "GINA 2023"
      ]
    },
    {
      "question": "Qual medida reduz o risco de candidíase oral devido aos corticosteróides inalados?",
      "options": [
        "Tome com leite",
        "Aumentar a dose",
        "Inspire profundamente",
        "Use câmara espaçadora"
      ],
      "correctAnswer": 4,
      "explanation": "O uso de câmara espaçadora diminui a deposição de corticosteroide na orofaringe, reduzindo significativamente o risco de candidíase oral e melhorando a deposição pulmonar do medicamento.",
      "hashtags": [
        "pneumologia",
        "asma",
        "prevenção",
        "câmara_espacial",
        "MEDICAL_TOPIC",
        "GEMA 5.2"
      ]
    },
    {
      "question": "Quando se considera que um paciente com asma apresenta boa adesão ao corticoide inalatório?",
      "options": [
        "Uso semanal alternativo",
        "Uso noturno isolado",
        "Uso diário sem esquecer",
        "Use apenas em crise"
      ],
      "correctAnswer": 3,
      "explanation": "A boa adesão ao tratamento de controle com corticoide inalatório implica o uso diário de acordo com o horário prescrito, sem esquecimentos significativos, para manter o controle da inflamação brônquica.",
      "hashtags": [
        "pneumologia",
        "asma",
        "adesão",
        "adesão_terapêutica",
        "MEDICAL_TOPIC",
        "GINA 2023"
      ]
    },
    {
      "question": "Qual é o principal mecanismo de ação dos agonistas beta2 de ação curta?",
      "options": [
        "Estimulação de adenilato ciclase",
        "Inibição da fosfodiesterase",
        "Bloqueio do receptor muscarínico",
        "Antagonismo do receptor H1"
      ],
      "correctAnswer": 1,
      "explanation": "Os agonistas beta2 de ação curta ativam o receptor beta2 adrenérgico, que estimula a adenilato ciclase e aumenta o AMPc, produzindo broncodilatação.",
      "hashtags": [
        "pneumologia",
        "asma",
        "farmacologia",
        "beta2_agonistas",
        "MEDICAL_TOPIC",
        "GINA 2023"
      ]
    },
    {
      "question": "Qual dos seguintes é um agonista beta2 de ação curta para uso inalado?",
      "options": [
        "Salmeterol",
        "Salbutamol",
        "Indacaterol",
        "Formoterol"
      ],
      "correctAnswer": 2,
      "explanation": "O salbutamol é um agonista beta2 de ação curta e de início rápido (SABA), enquanto o salmeterol, o formoterol e o indacaterol são de ação prolongada (LABA).",
      "hashtags": [
        "pneumologia",
        "asma",
        "tratamento",
        "sabia",
        "MEDICAL_TOPIC",
        "GINA 2023"
      ]
    },
    {
      "question": "Qual é a principal indicação dos agonistas beta2 de curta ação na asma?",
      "options": [
        "Monitoramento diário de sintomas",
        "Alívio rápido do broncoespasmo",
        "Tratamento de manutenção",
        "Prevenção de exacerbações"
      ],
      "correctAnswer": 2,
      "explanation": "Os SABAs são usados ​​como medicação de resgate para aliviar rapidamente o broncoespasmo agudo, e não como controle diário ou terapia de manutenção.",
      "hashtags": [
        "pneumologia",
        "asma",
        "indicações",
        "resgatar",
        "MEDICAL_TOPIC",
        "GINA 2023"
      ]
    },
    {
      "question": "Qual é um efeito colateral comum dos agonistas beta2 de ação curta?",
      "options": [
        "Hipotensão ortostática",
        "tosse persistente",
        "Hipercalemia",
        "Taquicardia sinusal"
      ],
      "correctAnswer": 4,
      "explanation": "A taquicardia é um efeito adverso comum da estimulação beta1 cruzada, embora a estimulação beta2 seja seletiva; Tremor e hipocalemia também podem ocorrer.",
      "hashtags": [
        "pneumologia",
        "asma",
        "efeitos_adversos",
        "taquicardia",
        "MEDICAL_TOPIC",
        "Goodman e Gilman 14ª edição"
      ]
    },
    {
      "question": "Qual via de administração é mais recomendada para agonistas beta2 de curta ação nas crises de asma?",
      "options": [
        "Via oral",
        "Via intravenosa",
        "Via subcutânea",
        "Rota inalada"
      ],
      "correctAnswer": 4,
      "explanation": "A via inalatória é preferida devido ao seu rápido início de ação, menor dose necessária e menos efeitos sistêmicos, utilizando nebulizador ou inalador dosimetrado.",
      "hashtags": [
        "pneumologia",
        "asma",
        "farmacocinética",
        "via_inalação",
        "MEDICAL_TOPIC",
        "GINA 2023"
      ]
    },
    {
      "question": "Qual é o tempo típico de início do salbutamol inalado?",
      "options": [
        "2 a 4 horas",
        "30 a 60 minutos",
        "15 a 30 minutos",
        "1 a 2 minutos"
      ],
      "correctAnswer": 4,
      "explanation": "O salbutamol inalado tem início de ação muito rápido, entre 1 e 2 minutos, com efeito máximo em 30-60 minutos e duração de 4 a 6 horas.",
      "hashtags": [
        "pneumologia",
        "asma",
        "farmacocinética",
        "ação_início",
        "MEDICAL_TOPIC",
        "GINA 2023"
      ]
    },
    {
      "question": "Qual é a principal indicação do corticosteróide sistêmico na asma?",
      "options": [
        "Rinite alérgica isolada",
        "Asma leve intermitente",
        "Ataque grave de asma",
        "Asma persistente leve"
      ],
      "correctAnswer": 3,
      "explanation": "Os corticosteróides sistêmicos são indicados nas crises graves de asma para controlar a inflamação brônquica aguda e prevenir a progressão para insuficiência respiratória.",
      "hashtags": [
        "medicina_interna",
        "asma",
        "tratamento",
        "corticosteróides_sistêmicos",
        "MEDICAL_TOPIC",
        "GINA 2023"
      ]
    },
    {
      "question": "Em que situação de asma os corticosteroides sistêmicos de rotina são contraindicados?",
      "options": [
        "Ataque moderado de asma",
        "Asma grave não controlada",
        "Asma persistente leve controlada",
        "Asma persistente moderada"
      ],
      "correctAnswer": 3,
      "explanation": "Na asma persistente leve controlada, os corticosteróides sistêmicos de rotina não são indicados, uma vez que o risco de efeitos adversos supera o benefício; o tratamento inalado é preferido.",
      "hashtags": [
        "medicina_interna",
        "asma",
        "contra-indicações",
        "asma_leve_controlada",
        "MEDICAL_TOPIC",
        "Guia GEMA 2024"
      ]
    },
    {
      "question": "Qual o corticosteróide sistêmico mais utilizado na crise asmática aguda?",
      "options": [
        "Beclometasona inalada",
        "budesonida inalada",
        "Prednisona oral",
        "Fluticasona inalada"
      ],
      "correctAnswer": 3,
      "explanation": "A prednisona oral é o corticosteroide sistêmico de escolha nas crises agudas de asma devido à sua rápida absorção, eficácia antiinflamatória e baixo custo.",
      "hashtags": [
        "farmacologia",
        "asma",
        "mecanismo_de_ação",
        "prednisona",
        "MEDICAL_TOPIC",
        "Harrison 21 anos"
      ]
    },
    {
      "question": "Qual é a duração típica do tratamento com corticosteróides sistêmicos em uma exacerbação de asma?",
      "options": [
        "5 a 7 dias",
        "Mais de 30 dias",
        "1 a 2 dias",
        "14 a 21 dias"
      ],
      "correctAnswer": 1,
      "explanation": "Nas exacerbações da asma, os corticosteróides sistêmicos são normalmente administrados por 5 a 7 dias, pois ciclos mais longos não apresentam benefícios adicionais e aumentam os efeitos adversos.",
      "hashtags": [
        "medicina_interna",
        "asma",
        "tratamento",
        "duração_tratamento",
        "MEDICAL_TOPIC",
        "GINA 2023"
      ]
    },
    {
      "question": "Qual das alternativas a seguir é um efeito adverso dos corticosteróides sistêmicos de longo prazo na asma?",
      "options": [
        "Hipercalemia",
        "Osteoporose",
        "Hipotensão ortostática",
        "Bradicardia sinusal"
      ],
      "correctAnswer": 2,
      "explanation": "A osteoporose é um efeito adverso bem documentado do uso prolongado de corticosteróides sistêmicos devido à inibição da formação óssea e aumento da reabsorção.",
      "hashtags": [
        "farmacologia",
        "asma",
        "efeitos_adversos",
        "osteoporose",
        "MEDICAL_TOPIC",
        "Atualização 2024"
      ]
    },
    {
      "question": "Qual critério clínico justifica o início de corticosteroides sistêmicos em uma crise de asma?",
      "options": [
        "Falta de resposta aos broncodilatadores",
        "Tosse seca sem dispneia",
        "Saturação de oxigênio > 95%",
        "PFE > 80% do previsto"
      ],
      "correctAnswer": 1,
      "explanation": "A falta de resposta aos broncodilatadores de curta ação indica obstrução grave e inflamação acentuada, justificando o início de corticosteróides sistêmicos para reduzir a inflamação.",
      "hashtags": [
        "medicina_interna",
        "asma",
        "tabela_clínica",
        "critérios_iniciais",
        "MEDICAL_TOPIC",
        "GEMA 2024---Harrison 21ed"
      ]
    },
    {
      "question": "Qual dos seguintes parâmetros define uma crise leve de asma de acordo com a classificação clínica?",
      "options": [
        "Fale em frases",
        "FR > 30 rpm",
        "Uso de músculos acessórios",
        "SatO2 < 90%"
      ],
      "correctAnswer": 1,
      "explanation": "Numa crise leve de asma o paciente consegue falar frases completas, sem grande dificuldade. Taquipneia >30 rpm, SatO2 <90% e uso de musculatura acessória indicam maior gravidade.",
      "hashtags": [
        "medicina_interna",
        "asma_crise",
        "tabela_clínica",
        "classificação_de_gravidade",
        "MEDICAL_TOPIC",
        "GEMA 5.4"
      ]
    },
    {
      "question": "Num ataque de asma moderado, a frequência cardíaca esperada é:",
      "options": [
        "60-80bpm",
        "100-120bpm",
        "80-100bpm",
        "> 130 bpm"
      ],
      "correctAnswer": 2,
      "explanation": "Em ataques moderados de asma, a frequência cardíaca geralmente fica entre 100 e 120 batimentos por minuto, refletindo a ativação simpática. Menos de 80 bpm é normal e >130 bpm sugere crise grave.",
      "hashtags": [
        "medicina_interna",
        "asma_crise",
        "tabela_clínica",
        "sinais_vitais",
        "MEDICAL_TOPIC",
        "GEMA 5.4"
      ]
    },
    {
      "question": "Qual achado de gasometria é característico de um ataque grave de asma?",
      "options": [
        "aumento da PaCO2",
        "PaO2 > 90 mmHg",
        "PaCO2 normal",
        "PaCO2 diminuída"
      ],
      "correctAnswer": 1,
      "explanation": "Na crise asmática grave, a hipoventilação alveolar leva à retenção de CO2 (aumento da PaCO2). Nas crises leves a moderadas, a PaCO2 costuma estar baixa devido à hiperventilação. PaO2 >90 mmHg não é típico.",
      "hashtags": [
        "medicina_interna",
        "asma_crise",
        "diagnóstico",
        "gasometria_arterial",
        "MEDICAL_TOPIC",
        "GEMA 5.4"
      ]
    },
    {
      "question": "Qual das alternativas a seguir é um critério para uma crise leve de asma de acordo com o PFE (pico de fluxo expiratório)?",
      "options": [
        "PEF 50-70% do teórico",
        "PFE < 33% do teórico",
        "PEF 33-50% do teórico",
        "PFE > 80% do teórico"
      ],
      "correctAnswer": 1,
      "explanation": "Nas crises leves de asma, o PFE é >70% do valor teórico. A faixa de 50-70% corresponde a parada moderada, 33-50% a grave e <33% a parada iminente. Portanto, >80% é leve.",
      "hashtags": [
        "medicina_interna",
        "asma_crise",
        "diagnóstico",
        "PEF expiratório",
        "MEDICAL_TOPIC",
        "GEMA 5.4"
      ]
    },
    {
      "question": "Na crise asmática, a presença de ‘tórax silencioso’ indica:",
      "options": [
        "crise grave",
        "Crise moderada",
        "Crise muito grave ou paralisação iminente",
        "Crise leve"
      ],
      "correctAnswer": 3,
      "explanation": "O 'tórax silencioso' é causado por obstrução tão grave que o fluxo de ar é mínimo, sem sons audíveis. É sinal de crise gravíssima ou parada respiratória iminente, e não de crise leve ou moderada.",
      "hashtags": [
        "medicina_interna",
        "asma_crise",
        "tabela_clínica",
        "ausculta pulmonar",
        "MEDICAL_TOPIC",
        "GEMA 5.4"
      ]
    },
    {
      "question": "Qual das alternativas a seguir NÃO é um critério para uma crise grave de asma?",
      "options": [
        "Fale em frases curtas",
        "SatO2 < 90%",
        "Uso de músculos acessórios",
        "PFE < 33% do teórico"
      ],
      "correctAnswer": 1,
      "explanation": "Falar em frases curtas é típico de uma crise moderada; Em casos graves, o paciente mal consegue dizer palavras isoladas ou não consegue falar. PFE <33%, SatO2 <90% e uso de acessórios são critérios de gravidade.",
      "hashtags": [
        "medicina_interna",
        "asma_crise",
        "tabela_clínica",
        "critérios_de_gravidade",
        "MEDICAL_TOPIC",
        "GEMA 5.4"
      ]
    },
    {
      "question": "Qual das alternativas a seguir é um sinal de gravidade em um ataque de asma?",
      "options": [
        "Tiragem supraclavicular",
        "Frequência cardíaca normal",
        "tosse produtiva",
        "Chiado audível"
      ],
      "correctAnswer": 1,
      "explanation": "A tiragem supraclavicular indica o uso de músculos acessórios, um sinal clássico de obstrução grave nas crises asmáticas.",
      "hashtags": [
        "medicina_interna",
        "asma",
        "tabela_clínica",
        "sinais_gravidade",
        "MEDICAL_TOPIC",
        ""
      ]
    },
    {
      "question": "Que achado físico sugere um ataque grave de asma?",
      "options": [
        "Frequência respiratória normal",
        "Expiração moderadamente prolongada",
        "Peito silencioso",
        "Chiado expiratório leve"
      ],
      "correctAnswer": 3,
      "explanation": "Peito silencioso indica fluxo aéreo mínimo devido à obstrução extrema, um sinal de gravidade iminente na asma.",
      "hashtags": [
        "medicina_interna",
        "asma",
        "tabela_clínica",
        "peito_silencioso",
        "MEDICAL_TOPIC",
        ""
      ]
    },
    {
      "question": "Qual é o critério de gravidade em uma crise de asma de acordo com o PEF?",
      "options": [
        "PFE inferior em 33%",
        "PFE entre 60-80%",
        "PFE superior a 80%",
        "PFE superior a 90%"
      ],
      "correctAnswer": 1,
      "explanation": "Um PFE (pico de fluxo expiratório) inferior a 33% do valor teórico indica uma crise grave de asma e requer tratamento urgente.",
      "hashtags": [
        "medicina_interna",
        "asma",
        "diagnóstico",
        "pef",
        "MEDICAL_TOPIC",
        "GEMA 2024"
      ]
    },
    {
      "question": "Qual das alternativas a seguir é um sinal de gravidade na asma infantil?",
      "options": [
        "Alargamento nasal",
        "Espirros frequentes",
        "Rinite alérgica",
        "tosse noturna leve"
      ],
      "correctAnswer": 1,
      "explanation": "A dilatação nasal é um sinal de dificuldade respiratória grave em crianças com crises de asma, indicando obstrução significativa.",
      "hashtags": [
        "pediatria",
        "infância_asma",
        "tabela_clínica",
        "vibração_nasal",
        "MEDICAL_TOPIC",
        ""
      ]
    },
    {
      "question": "Que alteração nos gases sanguíneos indica crise asmática grave?",
      "options": [
        "PaCO2 diminuída",
        "PaCO2 elevada",
        "pH alcalêmico",
        "PaO2 normal"
      ],
      "correctAnswer": 2,
      "explanation": "Nas crises graves de asma, a fadiga muscular pode aumentar a PaCO2 (hipercapnia), indicando insuficiência ventilatória iminente.",
      "hashtags": [
        "medicina_interna",
        "asma",
        "fisiopatologia",
        "hipercapnia",
        "MEDICAL_TOPIC",
        ""
      ]
    },
    {
      "question": "O que é um sinal de gravidade em um ataque de asma em adultos?",
      "options": [
        "Chiado expiratório",
        "Tosse seca ocasional",
        "Uso diário do inalador",
        "Dispneia ao falar"
      ],
      "correctAnswer": 4,
      "explanation": "A dispneia que impede a fala de frases completas é um sinal de obstrução grave e requer avaliação urgente em uma crise de asma.",
      "hashtags": [
        "medicina_interna",
        "asma",
        "tabela_clínica",
        "dispneia_fala",
        "MEDICAL_TOPIC",
        ""
      ]
    },
    {
      "question": "Qual é o broncodilatador de primeira linha na crise asmática?",
      "options": [
        "Ipratrópio nebulizado",
        "Teofilina intravenosa",
        "salbutamol inalado",
        "Adrenalina subcutânea"
      ],
      "correctAnswer": 3,
      "explanation": "O salbutamol (agonista beta-2 adrenérgico de curta ação) é o broncodilatador de primeira linha no tratamento agudo da asma devido ao seu rápido início de ação e perfil de segurança.",
      "hashtags": [
        "medicina_interna",
        "asma",
        "tratamento",
        "broncodilatadores",
        "MEDICAL_TOPIC",
        "GEMA 2024"
      ]
    },
    {
      "question": "Qual parâmetro orienta a oxigenoterapia na crise asmática grave?",
      "options": [
        "Saturação de oxigênio >92%",
        "Frequência cardíaca basal",
        "Pressão arterial média",
        "Pico de fluxo expiratório"
      ],
      "correctAnswer": 1,
      "explanation": "A oxigenoterapia em ataques asmáticos é titulada para manter uma saturação de oxigênio ≥92% (ou ≥95% em mulheres grávidas e crianças), uma vez que a hipoxemia é o principal risco de risco de vida.",
      "hashtags": [
        "medicina_interna",
        "asma",
        "tratamento",
        "oxigenoterapia",
        "MEDICAL_TOPIC",
        "GEMA 2024"
      ]
    },
    {
      "question": "Qual é o mecanismo de ação do salbutamol na asma aguda?",
      "options": [
        "Estimulação de receptores beta-2",
        "Antagonismo de leucotrienos",
        "Inibição da fosfodiesterase",
        "Bloqueio do receptor muscarínico"
      ],
      "correctAnswer": 1,
      "explanation": "O salbutamol é um agonista seletivo dos receptores beta-2 adrenérgicos, que produz relaxamento da musculatura lisa brônquica e broncodilatação rápida nas crises de asma.",
      "hashtags": [
        "farmacologia",
        "asma",
        "mecanismo_de_ação",
        "beta2_agonistas",
        "FARMACOLOGIA",
        "Katzung 15ed"
      ]
    },
    {
      "question": "Quando o ipratrópio nebulizado é indicado nas crises de asma?",
      "options": [
        "Apenas asma de esforço",
        "Crise inicial moderada ou grave",
        "Crise leve com pico de fluxo normal",
        "Manutenção da asma crônica"
      ],
      "correctAnswer": 2,
      "explanation": "O ipratrópio (anticolinérgico) é adicionado ao salbutamol nas crises moderadas ou graves desde o início, pois potencializa a broncodilatação e reduz a taxa de internação.",
      "hashtags": [
        "medicina_interna",
        "asma",
        "tratamento",
        "anticolinérgicos",
        "MEDICAL_TOPIC",
        "GEMA 2024"
      ]
    },
    {
      "question": "Qual é o sinal de gravidade que indica necessidade de oxigênio de alto fluxo?",
      "options": [
        "Frequência respiratória 18 rpm",
        "Uso de músculos acessórios",
        "Fluxo de pico >80% do teórico",
        "Saturação de oxigênio 88%"
      ],
      "correctAnswer": 4,
      "explanation": "Uma saturação de oxigênio <92% (por exemplo, 88%) indica hipoxemia significativa na crise asmática, necessitando de oxigênio suplementar de alto fluxo para corrigir a hipóxia tecidual.",
      "hashtags": [
        "medicina_interna",
        "asma",
        "tabela_clínica",
        "hipoxemia",
        "MEDICAL_TOPIC",
        "GEMA 2024"
      ]
    },
    {
      "question": "Qual via de administração é preferida para broncodilatadores em crises graves de asma?",
      "options": [
        "Via subcutânea",
        "Via inalada nebulizada",
        "Via oral",
        "via intramuscular"
      ],
      "correctAnswer": 2,
      "explanation": "Nas crises graves de asma, a via inalatória nebulizada (com máscara ou bocal) é preferida porque permite a administração de altas doses de broncodilatador diretamente nas vias aéreas com efeitos sistêmicos mínimos.",
      "hashtags": [
        "medicina_interna",
        "asma",
        "tratamento",
        "via_inalação",
        "MEDICAL_TOPIC",
        "GEMA 2024"
      ]
    }
  ]
}