{
  "questions": [
    {
      "question": "Qual é a principal função da medula espinhal como parte do SNC?",
      "options": [
        "Regular a temperatura corporal",
        "Transmitir informações bidirecionais",
        "Controle o ciclo do sono",
        "Processar informações visuais"
      ],
      "correctAnswer": 2,
      "explanation": "A medula espinhal atua como uma rodovia de informações, transmitindo sinais sensoriais ao cérebro e comandos motores ao corpo, além de ser um centro de reflexos.",
      "hashtags": [
        "medula espinhal_(neuroanatomia)",
        "função_geral",
        "conceito",
        "sistema_nervoso_central",
        "MEDICAL_TOPIC",
        ""
      ]
    },
    {
      "question": "De onde se origina a medula espinhal no crânio?",
      "options": [
        "Cadeira turca",
        "corpo esfenoidal",
        "Forame magno",
        "fossa craniana média"
      ],
      "correctAnswer": 3,
      "explanation": "A medula espinhal é contínua inferiormente com a medula oblonga, que por sua vez emerge do forame magno do osso occipital.",
      "hashtags": [
        "medula espinhal_(neuroanatomia)",
        "continuação_brain_stem",
        "macro_anatomia",
        "forame_magnum",
        "MEDICAL_TOPIC",
        ""
      ]
    },
    {
      "question": "Em que nível vertebral o cone medular geralmente termina em adultos?",
      "options": [
        "L1-L2",
        "L3-L4",
        "S1-S2",
        "T12-L1"
      ],
      "correctAnswer": 1,
      "explanation": "Nos adultos, a extremidade inferior da medula espinhal, conhecida como cone medular, geralmente termina entre a primeira e a segunda vértebras lombares (L1-L2).",
      "hashtags": [
        "medula espinhal_(neuroanatomia)",
        "cone_medular",
        "macro_anatomia",
        "terminação_medular",
        "MEDICAL_TOPIC",
        ""
      ]
    },
    {
      "question": "Como é chamado o feixe de raízes nervosas inferior ao cone medular?",
      "options": [
        "plexo sacral",
        "Filum terminal",
        "cone medular",
        "Cauda eqüina"
      ],
      "correctAnswer": 4,
      "explanation": "O conjunto de raízes nervosas lombares e sacrais que descem para o canal vertebral abaixo do cone medular é conhecido como cauda eqüina.",
      "hashtags": [
        "medula espinhal_(neuroanatomia)",
        "cauda_equina",
        "macro_anatomia",
        "estruturas_de_fluxo",
        "MEDICAL_TOPIC",
        ""
      ]
    },
    {
      "question": "Qual é a estrutura que ancora a medula espinhal em sua extremidade caudal?",
      "options": [
        "Filum terminal",
        "Dura mater",
        "Aracnóide",
        "ligamento denteado"
      ],
      "correctAnswer": 1,
      "explanation": "O filum terminale é um filamento fibroso que se origina no ápice do cone medular e desce até o cóccix, servindo como ponto de ancoragem para a medula.",
      "hashtags": [
        "medula espinhal_(neuroanatomia)",
        "filme_terminale",
        "macro_anatomia",
        "espinhal_anchorage",
        "MEDICAL_TOPIC",
        ""
      ]
    },
    {
      "question": "Quais estruturas nervosas se originam na intumescência cervical?",
      "options": [
        "nervos sacrais",
        "nervos lombares",
        "Nervos dos membros superiores",
        "nervos intercostais"
      ],
      "correctAnswer": 3,
      "explanation": "A intumescência cervical da medula espinhal dá origem aos nervos espinhais que inervam os membros superiores.",
      "hashtags": [
        "medula espinhal_(neuroanatomia)",
        "cervical_intumescência",
        "macro_anatomia",
        "inervação_extremidades",
        "MEDICAL_TOPIC",
        ""
      ]
    },
    {
      "question": "Qual é o número total de pares de nervos espinhais?",
      "options": [
        "23",
        "31",
        "55",
        "45"
      ],
      "correctAnswer": 2,
      "explanation": "A medula espinhal é segmentada e dela emergem 31 pares de nervos espinhais: 8 cervicais, 12 torácicos, 5 lombares, 5 sacrais e 1 coccígeo.",
      "hashtags": [
        "medula espinhal_(neuroanatomia)",
        "nervos_espinhais",
        "macro_anatomia",
        "segmentação_medular",
        "MEDICAL_TOPIC",
        ""
      ]
    },
    {
      "question": "Como a maioria dos nervos espinhais são numerados em relação às vértebras?",
      "options": [
        "Eles não estão diretamente relacionados",
        "Eles emergem em altura",
        "Eles emergem de baixo",
        "Eles emergem acima"
      ],
      "correctAnswer": 3,
      "explanation": "Do primeiro nervo torácico (T1), os nervos espinhais emergem abaixo da vértebra homônima, o que é diferente para os nervos cervicais superiores.",
      "hashtags": [
        "medula espinhal_(neuroanatomia)",
        "numeração_dos_nervos_espinhais",
        "macro_anatomia",
        "relacionamento_vertebral",
        "MEDICAL_TOPIC",
        ""
      ]
    },
    {
      "question": "Qual é o sulco mais proeminente na face ventral da medula espinhal?",
      "options": [
        "Sulco lateral",
        "Fissura média anterior",
        "sulco posterolateral",
        "sulco médio posterior"
      ],
      "correctAnswer": 2,
      "explanation": "A face ventral (anterior) da medula espinhal é marcada pela fissura mediana anterior, uma fenda profunda que separa as medulas ventrais.",
      "hashtags": [
        "medula espinhal_(neuroanatomia)",
        "anterior_middle_furrow",
        "macro_anatomia",
        "medula_faces",
        "MEDICAL_TOPIC",
        ""
      ]
    },
    {
      "question": "Onde emergem as raízes dorsais dos nervos espinhais?",
      "options": [
        "Sulco lateral",
        "sulco posterolateral",
        "sulco médio posterior",
        "sulco médio anterior"
      ],
      "correctAnswer": 2,
      "explanation": "As raízes dorsais (sensoriais) dos nervos espinhais emergem da medula espinhal através do sulco posterolateral.",
      "hashtags": [
        "medula espinhal_(neuroanatomia)",
        "raízes_dorsais",
        "macro_anatomia",
        "emergência_nervosa",
        "MEDICAL_TOPIC",
        ""
      ]
    },
    {
      "question": "Que tipo de células gliais formam a bainha de mielina na substância branca?",
      "options": [
        "Oligodendrócitos",
        "Células ependimárias",
        "Astrócitos",
        "Microglia"
      ],
      "correctAnswer": 1,
      "explanation": "Os oligodendrócitos são as células gliais do SNC responsáveis ​​pela formação da mielina que cobre os axônios da substância branca.",
      "hashtags": [
        "medula espinhal_(neuroanatomia)",
        "mielinização",
        "histologia",
        "substância_branca",
        "MEDICAL_TOPIC",
        ""
      ]
    },
    {
      "question": "Qual é a principal função dos astrócitos na medula espinhal?",
      "options": [
        "Transmissão de pulso",
        "Suporte estrutural e metabólico",
        "Fagocitose",
        "Produção de LCR"
      ],
      "correctAnswer": 2,
      "explanation": "Os astrócitos são as células gliais mais abundantes e fornecem suporte estrutural e nutricional e regulam o microambiente neuronal.",
      "hashtags": [
        "medula espinhal_(neuroanatomia)",
        "astrócitos",
        "histologia",
        "células_gliais",
        "MEDICAL_TOPIC",
        ""
      ]
    },
    {
      "question": "Qual é o formato da substância cinzenta no centro da medula espinhal?",
      "options": [
        "estrutura tubular",
        "Anel",
        "Cúspides irregulares",
        "H ou formato de borboleta"
      ],
      "correctAnswer": 4,
      "explanation": "A substância cinzenta medular possui organização central em forma de H ou borboleta, com projeções denominadas chifres.",
      "hashtags": [
        "medula espinhal_(neuroanatomia)",
        "substância_cinza",
        "organização_interna",
        "forma_medular",
        "MEDICAL_TOPIC",
        ""
      ]
    },
    {
      "question": "Que estrutura é encontrada no centro da substância cinzenta espinhal?",
      "options": [
        "corpo caloso",
        "duto central",
        "Tálamo",
        "Ventrículo lateral"
      ],
      "correctAnswer": 2,
      "explanation": "O ducto central (ou ducto ependimário) está localizado no centro da substância cinzenta medular e contém líquido cefalorraquidiano.",
      "hashtags": [
        "medula espinhal_(neuroanatomia)",
        "duto_central",
        "organização_interna",
        "substância_cinza",
        "MEDICAL_TOPIC",
        ""
      ]
    },
    {
      "question": "Que tipo de neurônios são encontrados principalmente nos cornos ventrais da substância cinzenta?",
      "options": [
        "interneurônios de associação",
        "Neurônios pré-ganglionares autônomos",
        "Neurônios motores somáticos",
        "neurônios sensoriais"
      ],
      "correctAnswer": 3,
      "explanation": "Os cornos ventrais (anteriores) da substância cinzenta medular abrigam os corpos celulares dos neurônios motores somáticos (neurônios motores alfa).",
      "hashtags": [
        "medula espinhal_(neuroanatomia)",
        "ventral_antlers",
        "organização_interna",
        "neurônios_motores",
        "MEDICAL_TOPIC",
        ""
      ]
    },
    {
      "question": "Onde estão localizados os neurônios pré-ganglionares autônomos na medula espinhal?",
      "options": [
        "Cadarços dorsais",
        "Chifres dorsais",
        "chifres ventrais",
        "chifres laterais"
      ],
      "correctAnswer": 4,
      "explanation": "Os cornos laterais da substância cinzenta, presentes nos segmentos torácico e lombar superior, contêm os corpos celulares dos neurônios pré-ganglionares autônomos.",
      "hashtags": [
        "medula espinhal_(neuroanatomia)",
        "chifres_laterais",
        "organização_interna",
        "sistema_autônomo",
        "MEDICAL_TOPIC",
        ""
      ]
    },
    {
      "question": "Qual a função dos interneurônios na medula espinhal?",
      "options": [
        "Conduzir impulsos sensoriais",
        "Forme a barreira hemato-espinhal",
        "Integre informações e gere padrões",
        "Transmitir comandos diretos do motor"
      ],
      "correctAnswer": 3,
      "explanation": "Os interneurônios são cruciais para a integração de informações, conectando neurônios aferentes e eferentes e desempenhando um papel nos reflexos e nos circuitos neuronais.",
      "hashtags": [
        "medula espinhal_(neuroanatomia)",
        "interneurônios",
        "organização_interna",
        "processamento_de_informações",
        "MEDICAL_TOPIC",
        ""
      ]
    },
    {
      "question": "Como a substância branca da medula espinhal é dividida em relação aos chifres cinzentos?",
      "options": [
        "Gânglios e plexos",
        "Colunas ou cabos",
        "Lóbulos, giros e sulcos",
        "Ventrículos e cavidades"
      ],
      "correctAnswer": 2,
      "explanation": "A substância branca circunda a substância cinzenta e está organizada em três pares de colunas ou cordões: dorsal, lateral e ventral.",
      "hashtags": [
        "medula espinhal_(neuroanatomia)",
        "substância_branca",
        "organização_interna",
        "divisão_medular",
        "MEDICAL_TOPIC",
        ""
      ]
    },
    {
      "question": "Que tipo de informação os tratos da medula dorsal transmitem principalmente?",
      "options": [
        "Dor e temperatura",
        "movimento voluntário",
        "Reflexos posturais",
        "Toque fino e propriocepção"
      ],
      "correctAnswer": 4,
      "explanation": "As medulas dorsais da medula espinhal contêm principalmente tratos ascendentes que transmitem informações sensoriais sobre toque fino, vibração e propriocepção.",
      "hashtags": [
        "medula espinhal_(neuroanatomia)",
        "cadarços_dorsais",
        "trechos_ascendentes",
        "sensibilidade_fina",
        "MEDICAL_TOPIC",
        ""
      ]
    },
    {
      "question": "Qual trato é a principal via motora voluntária para as extremidades?",
      "options": [
        "trato espinotalâmico",
        "Trato corticoespinhal lateral",
        "Trato espinocerebelar",
        "trato rubroespinhal"
      ],
      "correctAnswer": 2,
      "explanation": "O trato corticoespinhal lateral é a principal via descendente que controla o movimento voluntário fino das extremidades, originando-se no córtex e cruzando na medula.",
      "hashtags": [
        "medula espinhal_(neuroanatomia)",
        "lateral_corticopinal_tract",
        "extratos_descendentes",
        "controle_motor",
        "MEDICAL_TOPIC",
        ""
      ]
    },
    {
      "question": "Qual sistema transmite informações sobre dor e temperatura ao cérebro?",
      "options": [
        "sistema vestibuloespinhal",
        "Sistema coluna dorsal-lemnisco medial",
        "sistema espinotalâmico",
        "sistema espinocerebelar"
      ],
      "correctAnswer": 3,
      "explanation": "O sistema espinotalâmico é a principal via que transmite informações sobre dor, temperatura e toque grosseiro da medula espinhal para o tálamo e o córtex.",
      "hashtags": [
        "medula espinhal_(neuroanatomia)",
        "sistema espinotalâmico",
        "trechos_ascendentes",
        "dor_temperatura",
        "MEDICAL_TOPIC",
        ""
      ]
    },
    {
      "question": "Qual é a principal função do trato espinocerebelar?",
      "options": [
        "Regulação do tônus ​​muscular",
        "Controle motor fino dos dedos",
        "Transmissão de dor e temperatura",
        "Propriocepção inconsciente para equilíbrio"
      ],
      "correctAnswer": 4,
      "explanation": "O trato espinocerebelar transporta informações de propriocepção inconsciente para o cerebelo, sendo vital para a coordenação motora e o equilíbrio.",
      "hashtags": [
        "medula espinhal_(neuroanatomia)",
        "trato_espinocerebelar",
        "trechos_ascendentes",
        "coordenação_motora",
        "MEDICAL_TOPIC",
        ""
      ]
    },
    {
      "question": "Qual trato motor desce ipsilateralmente na medula ventral e cruza na medula?",
      "options": [
        "trato corticoespinhal anterior",
        "trato tectoespinhal",
        "trato reticuloespinhal",
        "trato rubroespinhal"
      ],
      "correctAnswer": 1,
      "explanation": "O trato corticoespinhal anterior desce ipsilateralmente no funículo ventral e cruza a linha média no nível segmentar da medula espinhal.",
      "hashtags": [
        "medula espinhal_(neuroanatomia)",
        "anterior_corticopinal_tract",
        "extratos_descendentes",
        "trunk_extremities_control",
        "MEDICAL_TOPIC",
        ""
      ]
    },
    {
      "question": "Qual camada meníngea é a mais externa e robusta, protegendo a medula espinhal?",
      "options": [
        "espaço epidural",
        "Dura mater",
        "Pia mater",
        "Aracnóide"
      ],
      "correctAnswer": 2,
      "explanation": "A dura-máter espinhal é a camada meníngea mais externa e mais forte, formada por tecido conjuntivo denso, que envolve a medula espinhal.",
      "hashtags": [
        "medula espinhal_(neuroanatomia)",
        "dura-máter",
        "meninges",
        "proteção espinhal",
        "MEDICAL_TOPIC",
        ""
      ]
    },
    {
      "question": "Qual é o espaço entre a dura-máter e a aracnóide espinhal?",
      "options": [
        "espaço subaracnóideo",
        "Espaço Lisker",
        "espaço epidural",
        "espaço subdural"
      ],
      "correctAnswer": 4,
      "explanation": "O espaço subdural está localizado entre a dura-máter e a aracnóide espinhal; É um espaço virtual que pode se tornar real em caso de hemorragia.",
      "hashtags": [
        "medula espinhal_(neuroanatomia)",
        "espaço_subdural",
        "meninges",
        "espaços_meníngeos",
        "MEDICAL_TOPIC",
        ""
      ]
    },
    {
      "question": "O que contém o espaço subaracnóideo da medula espinhal?",
      "options": [
        "Líquido cefalorraquidiano",
        "sangue venoso",
        "nervos espinhais",
        "tecido adiposo"
      ],
      "correctAnswer": 1,
      "explanation": "O espaço subaracnóideo, localizado entre a aracnóide e a pia-máter, é preenchido com líquido cefalorraquidiano (LCR), que atua como amortecedor.",
      "hashtags": [
        "medula espinhal_(neuroanatomia)",
        "espaço_subaracnóide",
        "meninges",
        "fluido_cerebrospinal",
        "MEDICAL_TOPIC",
        ""
      ]
    },
    {
      "question": "Que estrutura ajuda a manter a medula espinhal centrada no canal vertebral?",
      "options": [
        "raízes nervosas",
        "plexos venosos",
        "Filum terminal",
        "ligamentos dentados"
      ],
      "correctAnswer": 4,
      "explanation": "Os ligamentos dentados são espessamentos laterais da pia-máter que se fixam à dura-máter, ajudando a manter a medula espinhal centrada e protegida lateralmente.",
      "hashtags": [
        "medula espinhal_(neuroanatomia)",
        "ligamentos_dentados",
        "meninges",
        "suporte espinhal",
        "MEDICAL_TOPIC",
        ""
      ]
    },
    {
      "question": "Qual o tanque preferido para punção lombar?",
      "options": [
        "cisterna pontocerebelar",
        "Grande cisterna",
        "cisterna do quiasma",
        "cisterna lombar"
      ],
      "correctAnswer": 4,
      "explanation": "A cisterna lombar, que é uma dilatação do espaço subaracnóideo na região lombar abaixo de L2, é o local de escolha para a punção lombar.",
      "hashtags": [
        "medula espinhal_(neuroanatomia)",
        "cisterna_lombar",
        "meninges",
        "punção_lombar",
        "MEDICAL_TOPIC",
        ""
      ]
    },
    {
      "question": "Qual artéria é crucial para irrigar os dois terços inferiores da medula espinhal?",
      "options": [
        "Artéria Adamkiewicz",
        "artéria espinhal anterior",
        "artéria espinhal posterior",
        "Artéria vertebral"
      ],
      "correctAnswer": 1,
      "explanation": "A artéria radicular maior, conhecida como artéria de Adamkiewicz, é a principal artéria que irriga os dois terços inferiores da medula espinhal.",
      "hashtags": [
        "medula espinhal_(neuroanatomia)",
        "adamkiewicz_artery",
        "contribuição_sangue",
        "irrigação_medular",
        "MEDICAL_TOPIC",
        ""
      ]
    },
    {
      "question": "Que síndrome pode resultar da oclusão da artéria espinhal anterior?",
      "options": [
        "Síndrome de Horner",
        "Síndrome de Wallenberg",
        "Síndrome de Brown-Séquard",
        "Síndrome de infarto espinhal anterior"
      ],
      "correctAnswer": 4,
      "explanation": "A oclusão da artéria espinhal anterior, que irriga os dois terços anteriores da medula espinhal, pode causar síndrome de infarto espinhal anterior com paraplegia e perda sensorial.",
      "hashtags": [
        "medula espinhal_(neuroanatomia)",
        "infarto_espinhal anterior",
        "contribuição_sangue",
        "patologia_vascular",
        "MEDICAL_TOPIC",
        ""
      ]
    },
    {
      "question": "Qual é a característica dos plexos venosos vertebrais internos da medula espinhal?",
      "options": [
        "Eles drenam exclusivamente para a medula",
        "Eles têm válvulas eficientes",
        "Permitir fluxo sanguíneo bidirecional",
        "Eles são a principal fonte de LCR"
      ],
      "correctAnswer": 3,
      "explanation": "Os plexos venosos vertebrais internos não possuem válvulas, permitindo o fluxo sanguíneo bidirecional e facilitando a propagação de infecções ou metástases.",
      "hashtags": [
        "medula espinhal_(neuroanatomia)",
        "plexos_venosos vertebrais",
        "contribuição_sangue",
        "circulação_venosa",
        "MEDICAL_TOPIC",
        ""
      ]
    },
    {
      "question": "Qual via nervosa transmite a sensação de posição do corpo (propriocepção)?",
      "options": [
        "sistema corticoespinhal",
        "Sistema coluna dorsal-lemnisco medial",
        "sistema espinotalâmico",
        "sistema espinocerebelar"
      ],
      "correctAnswer": 2,
      "explanation": "O sistema coluna dorsal-lemnisco medial é responsável por transmitir informações sobre propriocepção (sensação de posição do corpo), vibração e toque fino discriminativo.",
      "hashtags": [
        "medula espinhal_(neuroanatomia)",
        "sistema_coluna_dorsal",
        "trechos_ascendentes",
        "propriocepção",
        "MEDICAL_TOPIC",
        ""
      ]
    },
    {
      "question": "Qual a função do trato rubroespinhal na medula espinhal?",
      "options": [
        "Influência nos músculos flexores das extremidades superiores",
        "Manter o equilíbrio postural",
        "Transmissão da dor",
        "Controle motor fino dos dedos"
      ],
      "correctAnswer": 1,
      "explanation": "O trato rubroespinhal origina-se no mesencéfalo e desce na medula lateral, influenciando a atividade motora, principalmente dos músculos flexores das extremidades superiores.",
      "hashtags": [
        "medula espinhal_(neuroanatomia)",
        "rubroespinhal_tract",
        "extratos_descendentes",
        "control_extremidades_superiores",
        "MEDICAL_TOPIC",
        ""
      ]
    },
    {
      "question": "Qual é o principal componente do arco reflexo que detecta o estímulo?",
      "options": [
        "Efetor",
        "neurônio motor",
        "Centro de integração",
        "Receptor"
      ],
      "correctAnswer": 4,
      "explanation": "O receptor é a estrutura especializada que detecta o estímulo específico e o converte em um sinal nervoso, iniciando o arco reflexo.",
      "hashtags": [
        "medula espinhal_(neuroanatomia)",
        "arco_reflexo",
        "reflexos espinhais",
        "componentes_reflexos",
        "MEDICAL_TOPIC",
        ""
      ]
    },
    {
      "question": "Que tipo de sinapse caracteriza o reflexo reflexo do joelho?",
      "options": [
        "inibitório direto",
        "Polissináptico",
        "Autossináptico",
        "Monossináptico"
      ],
      "correctAnswer": 4,
      "explanation": "O reflexo reflexo do joelho é um exemplo clássico de reflexo monossináptico, onde o neurônio sensorial faz sinapse diretamente com o neurônio motor alfa.",
      "hashtags": [
        "medula espinhal_(neuroanatomia)",
        "reflexo_patela",
        "reflexos espinhais",
        "tipos_reflexos",
        "MEDICAL_TOPIC",
        ""
      ]
    },
    {
      "question": "Que reflexo protege o corpo da tensão muscular excessiva no tendão?",
      "options": [
        "Reflexo flexor",
        "reflexo de estiramento",
        "Reflexo Cruzado de Extensão",
        "Reflexo do tendão de Golgi"
      ],
      "correctAnswer": 4,
      "explanation": "Os reflexos do tendão de Golgi, desencadeados pela tensão excessiva nos órgãos tendinosos, causam relaxamento muscular para prevenir danos.",
      "hashtags": [
        "medula espinhal_(neuroanatomia)",
        "golgi_tendon_reflex",
        "reflexos espinhais",
        "proteção muscular",
        "MEDICAL_TOPIC",
        ""
      ]
    },
    {
      "question": "O que acontece no membro ipsilateral durante um reflexo de retirada devido a estímulos dolorosos?",
      "options": [
        "extensão muscular",
        "Contração isométrica",
        "flexão muscular",
        "Relaxamento completo"
      ],
      "correctAnswer": 3,
      "explanation": "Num reflexo de retirada (flexor), o membro exposto ao estímulo doloroso flexiona-se para longe do dano, ativando os músculos flexores.",
      "hashtags": [
        "medula espinhal_(neuroanatomia)",
        "reflexo_flexor",
        "reflexos espinhais",
        "dor_retirada",
        "MEDICAL_TOPIC",
        ""
      ]
    },
    {
      "question": "Qual reflexo ocorre simultaneamente com o reflexo flexor no membro contralateral?",
      "options": [
        "Reflexo do tendão de Golgi",
        "Reflexo de retirada",
        "reflexo de estiramento",
        "Reflexo Cruzado de Extensão"
      ],
      "correctAnswer": 4,
      "explanation": "O reflexo de extensão cruzada, que ocorre no membro contralateral durante um reflexo de retirada, ajuda a manter o equilíbrio ao estender a perna de apoio.",
      "hashtags": [
        "medula espinhal_(neuroanatomia)",
        "extensão_reflex_cruzada",
        "reflexos espinhais",
        "equilíbrio_postural",
        "MEDICAL_TOPIC",
        ""
      ]
    },
    {
      "question": "O que a hiperreflexia pode indicar em um exame neurológico?",
      "options": [
        "Déficit na junção neuromuscular",
        "Danos aos neurônios motores periféricos",
        "Disfunção do receptor",
        "Lesões nas vias motoras descendentes"
      ],
      "correctAnswer": 4,
      "explanation": "A hiperreflexia (reflexos exagerados) muitas vezes indica uma lesão das vias motoras descendentes, como o trato corticoespinhal, que perdem sua influência inibitória sobre os reflexos espinhais.",
      "hashtags": [
        "medula espinhal_(neuroanatomia)",
        "hiperreflexia",
        "reflexos espinhais",
        "lesões_coluna",
        "MEDICAL_TOPIC",
        ""
      ]
    },
    {
      "question": "O que a hiporreflexia geralmente indica no exame neurológico?",
      "options": [
        "Lesão medular suprassegmentar",
        "Superestimulação do sistema nervoso",
        "Danos ao receptor, nervo periférico ou neurônio motor",
        "Problemas nas vias motoras descendentes"
      ],
      "correctAnswer": 3,
      "explanation": "A hiporreflexia (reflexos diminuídos ou ausentes) pode ser devida a patologias que afetam os componentes do arco reflexo, como o receptor, o neurônio sensorial, o neurônio motor ou a junção neuromuscular.",
      "hashtags": [
        "medula espinhal_(neuroanatomia)",
        "hiporreflexia",
        "reflexos espinhais",
        "patologia_neurológica",
        "MEDICAL_TOPIC",
        ""
      ]
    },
    {
      "question": "Qual característica da medula espinhal humana está relacionada à manipulação fina das extremidades superiores?",
      "options": [
        "Intumescência cervical bem desenvolvida",
        "Filum terminal longo",
        "cone medular alto",
        "Extensa cauda eqüina"
      ],
      "correctAnswer": 1,
      "explanation": "A intumescência cervical é um espessamento da medula espinhal de onde emergem os nervos dos membros superiores e seu desenvolvimento é crucial para a destreza manual humana.",
      "hashtags": [
        "medula espinhal_(neuroanatomia)",
        "cervical_intumescência",
        "neuroanatomia comparativa",
        "extremidades_superiores",
        "MEDICAL_TOPIC",
        ""
      ]
    },
    {
      "question": "Como a terminação do cone medular geralmente difere nos mamíferos quadrúpedes em comparação aos humanos?",
      "options": [
        "É mais fluxo",
        "Não há diferença significativa",
        "É mais rostral",
        "Está no nível T12"
      ],
      "correctAnswer": 1,
      "explanation": "Em mamíferos quadrúpedes, o cone medular tende a terminar em um nível vertebral mais caudal (por exemplo, L5-S1) em comparação com o nível L1-L2 em humanos.",
      "hashtags": [
        "medula espinhal_(neuroanatomia)",
        "cone_medular",
        "neuroanatomia comparativa",
        "mamíferos_quadrúpedes",
        "MEDICAL_TOPIC",
        ""
      ]
    },
    {
      "question": "Que adaptação é observada na medula espinhal das aves para o voo?",
      "options": [
        "Redução no número de nervos espinhais",
        "Ausência de matéria cinzenta",
        "Intumescências cervicais e lombares muito marcadas",
        "Maior desenvolvimento da medula dorsal"
      ],
      "correctAnswer": 3,
      "explanation": "As aves possuem intumescências cervicais e lombossacrais muito proeminentes, essenciais para o controle motor das asas e pernas, adaptações cruciais para o vôo e movimento.",
      "hashtags": [
        "medula espinhal_(neuroanatomia)",
        "pássaros",
        "neuroanatomia comparativa",
        "adaptações_de_voo",
        "MEDICAL_TOPIC",
        ""
      ]
    },
    {
      "question": "Que característica da medula espinhal das cobras está adaptada ao movimento do corpo?",
      "options": [
        "Presença de múltiplas intumescências",
        "Comprimento curto e sem segmentos",
        "Terminação cervical",
        "Extremamente alongado e cilíndrico"
      ],
      "correctAnswer": 4,
      "explanation": "As cobras possuem uma medula espinhal muito alongada que percorre toda a extensão do corpo, adaptada ao controle dos movimentos ondulatórios e à inervação dos músculos axiais e caudais.",
      "hashtags": [
        "medula espinhal_(neuroanatomia)",
        "cobras",
        "neuroanatomia comparativa",
        "movimento_corpo",
        "MEDICAL_TOPIC",
        ""
      ]
    },
    {
      "question": "Como o desenvolvimento do sistema corticoespinhal está relacionado à destreza motora em diferentes espécies?",
      "options": [
        "É mais desenvolvido em espécies com controle motor fino",
        "É mais simples em primatas",
        "Está presente apenas em anfíbios",
        "Varia inversamente com a massa cerebral"
      ],
      "correctAnswer": 1,
      "explanation": "O sistema corticoespinhal, responsável pelo controle motor voluntário fino, é significativamente mais desenvolvido em espécies com maior destreza motora, como os primatas, especialmente os humanos.",
      "hashtags": [
        "medula espinhal_(neuroanatomia)",
        "trato_corticoespinhal",
        "neuroanatomia comparativa",
        "controle_de_motor_fino",
        "MEDICAL_TOPIC",
        ""
      ]
    },
    {
      "question": "Qual é a principal via de inervação motora voluntária da face?",
      "options": [
        "trato corticoespinhal",
        "trato reticuloespinhal",
        "trato espinotalâmico",
        "trato corticobulbar"
      ],
      "correctAnswer": 4,
      "explanation": "O trato corticobulbar, originado no córtex motor, desce para inervar os núcleos dos nervos cranianos no tronco encefálico, controlando a musculatura da face.",
      "hashtags": [
        "medula espinhal_(neuroanatomia)",
        "corticobulbar_tract",
        "face_motor_control",
        "caminhos_nervosos",
        "MEDICAL_TOPIC",
        ""
      ]
    },
    {
      "question": "Qual via neural é crucial para a integração das informações sensoriais e motoras nos reflexos?",
      "options": [
        "Leptomeninge",
        "interneurônios espinhais",
        "Via extrapiramidal",
        "forma piramidal"
      ],
      "correctAnswer": 2,
      "explanation": "Os interneurônios espinhais são fundamentais para a integração de sinais entre neurônios aferentes e eferentes, permitindo a complexidade dos reflexos e dos circuitos neuronais.",
      "hashtags": [
        "medula espinhal_(neuroanatomia)",
        "interneurônios",
        "caminhos_nervosos",
        "integração_neural",
        "MEDICAL_TOPIC",
        ""
      ]
    },
    {
      "question": "Como é chamada a função dos neurônios motores alfa na medula espinhal?",
      "options": [
        "Neurônios pré-ganglionares",
        "Neurônios aferentes primários",
        "neurônios de associação",
        "Neurônios motores somáticos"
      ],
      "correctAnswer": 4,
      "explanation": "Os neurônios motores alfa, localizados nos cornos ventrais da substância cinzenta, são neurônios motores somáticos cujos axônios inervam os músculos esqueléticos.",
      "hashtags": [
        "medula espinhal_(neuroanatomia)",
        "alfa_motor_neurônios",
        "organização_interna",
        "inervação muscular",
        "MEDICAL_TOPIC",
        ""
      ]
    },
    {
      "question": "Qual o efeito da transecção do trato corticoespinhal no controle motor?",
      "options": [
        "Aumento do tônus ​​muscular espástico",
        "Perda de controle voluntário fino",
        "Controle fino aprimorado",
        "Reflexos melhorados"
      ],
      "correctAnswer": 2,
      "explanation": "A interrupção do trato corticoespinhal, a principal via do movimento voluntário fino, resulta em fraqueza e perda da capacidade de realizar movimentos precisos.",
      "hashtags": [
        "medula espinhal_(neuroanatomia)",
        "trato_corticoespinhal",
        "controle_motor",
        "déficit_motor",
        "MEDICAL_TOPIC",
        ""
      ]
    },
    {
      "question": "Qual é a função do núcleo vermelho em relação à medula espinhal?",
      "options": [
        "Processamento sensorial",
        "Origem do trato rubroespinhal",
        "Caminho para propriocepção",
        "Controle dos reflexos autonômicos"
      ],
      "correctAnswer": 2,
      "explanation": "O núcleo vermelho, localizado no mesencéfalo, é a origem do trato rubroespinhal, uma via motora descendente que influencia a atividade muscular.",
      "hashtags": [
        "medula espinhal_(neuroanatomia)",
        "núcleo_vermelho",
        "extratos_descendentes",
        "tronco cerebral",
        "MEDICAL_TOPIC",
        ""
      ]
    },
    {
      "question": "Qual sistema extrapiramidal ajuda a manter o equilíbrio postural e o tônus ​​muscular?",
      "options": [
        "trato tectoespinhal",
        "trato reticuloespinhal",
        "Trato vestibulospinal",
        "trato rubroespinhal"
      ],
      "correctAnswer": 3,
      "explanation": "O trato vestibulospinal origina-se nos núcleos vestibulares do tronco encefálico e desempenha um papel crucial na manutenção do equilíbrio e da postura, modulando o tônus ​​muscular.",
      "hashtags": [
        "medula espinhal_(neuroanatomia)",
        "vestibulospinal_tract",
        "extratos_descendentes",
        "equilíbrio",
        "MEDICAL_TOPIC",
        ""
      ]
    },
    {
      "question": "Que tipo de medula espinhal os peixes se adaptaram para nadar?",
      "options": [
        "Reto e cilíndrico",
        "Com intumescências marcadas",
        "Muito curto e grosso",
        "Com lobos laterais desenvolvidos"
      ],
      "correctAnswer": 1,
      "explanation": "A medula espinhal dos peixes é tipicamente reta e cilíndrica, estendendo-se por todo o comprimento do corpo, adaptada para o controle da natação e do movimento hidrodinâmico.",
      "hashtags": [
        "medula espinhal_(neuroanatomia)",
        "peixe",
        "neuroanatomia comparativa",
        "adaptação_aquática",
        "MEDICAL_TOPIC",
        ""
      ]
    },
    {
      "question": "Quais componentes do arco reflexo conectam o SNC ao efetor?",
      "options": [
        "Neurônio motor e efetor",
        "Centro integrador e receptor",
        "Receptor e neurônio sensorial",
        "Neurônio sensorial e centro integrador"
      ],
      "correctAnswer": 1,
      "explanation": "O neurônio motor (eferente) é aquele que transporta o impulso nervoso da medula espinhal (centro integrador) até o efetor (músculo ou glândula), causando a resposta.",
      "hashtags": [
        "medula espinhal_(neuroanatomia)",
        "arco_reflexo",
        "neurônio motor",
        "componentes_reflexos",
        "MEDICAL_TOPIC",
        ""
      ]
    },
    {
      "question": "O que são os órgãos tendinosos de Golgi e que reflexos eles desencadeiam?",
      "options": [
        "Receptores de estresse; reflexo de inibição",
        "Receptores de estiramento; reflexo de estiramento",
        "Receptores de vibração; reflexo de propriocepção",
        "Nociceptores; reflexo de retirada"
      ],
      "correctAnswer": 1,
      "explanation": "Os órgãos tendinosos de Golgi são receptores de tensão localizados nos tendões musculares que, quando ativados por tensão excessiva, desencadeiam um reflexo de inibição para relaxar o músculo.",
      "hashtags": [
        "medula espinhal_(neuroanatomia)",
        "golgi_tendinous_organ",
        "reflexos espinhais",
        "receptores_sensoriais",
        "MEDICAL_TOPIC",
        ""
      ]
    },
    {
      "question": "Qual é a implicação clínica das veias epidurais sem válvula?",
      "options": [
        "Eles permitem a propagação de metástases",
        "Garanta fluxo unidirecional",
        "Eles facilitam a trombose",
        "Eles previnem infecções"
      ],
      "correctAnswer": 1,
      "explanation": "A ausência de válvulas nos plexos venosos vertebrais internos (localizados no espaço epidural) permite o fluxo sanguíneo bidirecional, o que pode facilitar a disseminação de células cancerígenas (metástases) para a coluna vertebral.",
      "hashtags": [
        "medula espinhal_(neuroanatomia)",
        "veias_epidural",
        "contribuição_sangue",
        "metástase",
        "MEDICAL_TOPIC",
        ""
      ]
    },
    {
      "question": "Qual par de nervos espinhais é particularmente numerado em relação às vértebras?",
      "options": [
        "nervos sacrais",
        "Nervos torácicos",
        "Nervos cervicais",
        "nervos lombares"
      ],
      "correctAnswer": 3,
      "explanation": "Os nervos cervicais, diferentemente dos de outras regiões, possuem uma numeração peculiar: C1-C7 emergem acima da vértebra homônima, mas C8 emerge abaixo de C7.",
      "hashtags": [
        "medula espinhal_(neuroanatomia)",
        "nervos_cervicais",
        "macro_anatomia",
        "numeração_vertebral",
        "MEDICAL_TOPIC",
        ""
      ]
    },
    {
      "question": "Qual camada meníngea está intimamente ligada à superfície da medula espinhal?",
      "options": [
        "Aracnóide",
        "espaço epidural",
        "Pia mater",
        "Dura mater"
      ],
      "correctAnswer": 3,
      "explanation": "A pia-máter é a camada meníngea mais interna e delicada, que adere intimamente à superfície da medula espinhal, seguindo todos os seus contornos.",
      "hashtags": [
        "medula espinhal_(neuroanatomia)",
        "pia mater",
        "meninges",
        "camadas_medulares",
        "MEDICAL_TOPIC",
        ""
      ]
    },
    {
      "question": "Qual é o resultado esperado de uma lesão que afeta o trato espinotalâmico?",
      "options": [
        "Paralisia espástica",
        "Dificuldade de coordenação",
        "Perda de dor e temperatura",
        "Perda de propriocepção"
      ],
      "correctAnswer": 3,
      "explanation": "Uma lesão do trato espinotalâmico resulta na interrupção da transmissão de informações sobre dor e temperatura, levando à perda dessas sensibilidades.",
      "hashtags": [
        "medula espinhal_(neuroanatomia)",
        "trato_espinotalâmico",
        "déficit_sensorial",
        "dor_temperatura",
        "MEDICAL_TOPIC",
        ""
      ]
    },
    {
      "question": "Qual a função dos oligodendrócitos na substância branca?",
      "options": [
        "Produção de LCR",
        "Formação da bainha de mielina",
        "Suporte metabólico",
        "Fagocitose"
      ],
      "correctAnswer": 2,
      "explanation": "Os oligodendrócitos são células gliais do SNC responsáveis ​​pela mielinização dos axônios da substância branca, formando a bainha de mielina que acelera a condução nervosa.",
      "hashtags": [
        "medula espinhal_(neuroanatomia)",
        "oligodendrócitos",
        "substância_branca",
        "mielinização",
        "MEDICAL_TOPIC",
        ""
      ]
    },
    {
      "question": "Por que as raízes nervosas são inferiores ao cone medular chamadas cauda eqüina?",
      "options": [
        "Devido à sua cor branca",
        "Devido à sua origem embrionária",
        "Devido à sua função autônoma",
        "Por causa de seu formato de rabo de cavalo"
      ],
      "correctAnswer": 4,
      "explanation": "A cauda equina recebe esse nome devido à sua aparência de rabo de cavalo, devido ao feixe de longas raízes nervosas lombares e sacrais que descem para o canal vertebral.",
      "hashtags": [
        "medula espinhal_(neuroanatomia)",
        "cauda_equina",
        "macro_anatomia",
        "terminologia_anatômica",
        "MEDICAL_TOPIC",
        ""
      ]
    },
    {
      "question": "Quais artérias formam a principal artéria espinhal anterior?",
      "options": [
        "artérias intercostais",
        "artérias radiculares",
        "Artérias espinhais posteriores",
        "artérias vertebrais"
      ],
      "correctAnswer": 4,
      "explanation": "A principal artéria espinhal anterior surge das artérias vertebrais, que descem e se unem para formar uma artéria longitudinal ao longo da medula espinhal.",
      "hashtags": [
        "medula espinhal_(neuroanatomia)",
        "artéria_espinhal anterior",
        "contribuição_sangue",
        "artérias_vertebrais",
        "MEDICAL_TOPIC",
        ""
      ]
    },
    {
      "question": "Qual é a função da barreira hemato-espinhal?",
      "options": [
        "Facilitar a passagem de todos os nutrientes",
        "Aumentar a vascularização do SNC",
        "Permitir a entrada rápida de toxinas",
        "Regular a passagem de substâncias entre o sangue e o tecido nervoso"
      ],
      "correctAnswer": 4,
      "explanation": "A barreira hemato-espinhal, formada pelas células endoteliais dos capilares espinhais e dos pés dos astrócitos, regula seletivamente a passagem de substâncias, protegendo o tecido nervoso.",
      "hashtags": [
        "medula espinhal_(neuroanatomia)",
        "barreira_sangue_espinhal",
        "histologia",
        "proteção_de_tecido_nervoso",
        "MEDICAL_TOPIC",
        ""
      ]
    },
    {
      "question": "Qual via motora se origina na formação reticular do tronco cerebral?",
      "options": [
        "trato rubroespinhal",
        "trato corticoespinhal",
        "trato reticuloespinhal",
        "Trato vestibulospinal"
      ],
      "correctAnswer": 3,
      "explanation": "O trato reticulospinal origina-se na formação reticular do tronco encefálico e desce até a medula espinhal, influenciando o tônus ​​muscular e a atividade motora automática.",
      "hashtags": [
        "medula espinhal_(neuroanatomia)",
        "trato_reticulospinal",
        "extratos_descendentes",
        "controle_automático",
        "MEDICAL_TOPIC",
        ""
      ]
    },
    {
      "question": "Qual é o objetivo principal dos reflexos espinhais?",
      "options": [
        "Respostas rápidas para proteção e homeostase",
        "Processamento complexo de informações",
        "comunicação de longa distância",
        "Geração de pensamento consciente"
      ],
      "correctAnswer": 1,
      "explanation": "Os reflexos espinhais são respostas rápidas e involuntárias destinadas a proteger o corpo de danos e manter a homeostase, mediadas por circuitos na medula espinhal.",
      "hashtags": [
        "medula espinhal_(neuroanatomia)",
        "reflexos espinhais",
        "função_reflexo",
        "homeostase",
        "MEDICAL_TOPIC",
        ""
      ]
    },
    {
      "question": "O que o neurônio motor reflexo do joelho faz?",
      "options": [
        "Cruze a linha média",
        "Ative diretamente o músculo quadríceps",
        "Detectar estiramento",
        "Inibir o músculo antagonista"
      ],
      "correctAnswer": 2,
      "explanation": "No reflexo reflexo do joelho, o neurônio motor alfa que emerge da medula espinhal inerva diretamente o músculo quadríceps, fazendo com que ele se contraia.",
      "hashtags": [
        "medula espinhal_(neuroanatomia)",
        "reflexo_patela",
        "neurônio motor",
        "ação_muscular",
        "MEDICAL_TOPIC",
        ""
      ]
    },
    {
      "question": "Que tipo de resposta é produzida no músculo antagonista durante o reflexo patelar?",
      "options": [
        "Inibição (relaxamento)",
        "Estimulação nervosa constante",
        "leve contração",
        "forte contração"
      ],
      "correctAnswer": 1,
      "explanation": "O reflexo reflexo do joelho envolve inibição recíproca: enquanto o quadríceps se contrai, o músculo isquiotibial (antagonista) relaxa para permitir a extensão do joelho.",
      "hashtags": [
        "medula espinhal_(neuroanatomia)",
        "reflexo_patela",
        "inibição_recíproca",
        "músculos_antagonistas",
        "MEDICAL_TOPIC",
        ""
      ]
    },
    {
      "question": "Qual sistema da medula espinhal controla o movimento voluntário fino dos dedos?",
      "options": [
        "sistema vestibuloespinhal",
        "sistema corticoespinhal lateral",
        "sistema espinotalâmico",
        "sistema espinocerebelar"
      ],
      "correctAnswer": 2,
      "explanation": "O trato corticoespinhal lateral é a principal via descendente para o controle do movimento voluntário fino e preciso, especialmente das extremidades, incluindo os dedos.",
      "hashtags": [
        "medula espinhal_(neuroanatomia)",
        "lateral_corticopinal_tract",
        "controle_de_motor_fino",
        "membros",
        "MEDICAL_TOPIC",
        ""
      ]
    },
    {
      "question": "Qual é a substância que cobre os axônios da medula espinhal e permite a condução nervosa rápida?",
      "options": [
        "mielina",
        "matéria cinzenta",
        "Axônio",
        "Astrócito"
      ],
      "correctAnswer": 1,
      "explanation": "A mielina é uma cobertura lipídica isolante que envolve muitos axônios na substância branca da medula espinhal, permitindo a rápida condução dos impulsos nervosos.",
      "hashtags": [
        "medula espinhal_(neuroanatomia)",
        "mielina",
        "substância_branca",
        "condução_nervosa",
        "MEDICAL_TOPIC",
        ""
      ]
    },
    {
      "question": "Que estrutura é formada pela união das raízes dorsal e ventral dos nervos espinhais?",
      "options": [
        "plexo nervoso",
        "gânglio da raiz dorsal",
        "medula espinhal",
        "nervo espinhal"
      ],
      "correctAnswer": 4,
      "explanation": "As raízes dorsal (sensorial) e ventral (motora) se fundem para formar cada um dos 31 pares de nervos espinhais.",
      "hashtags": [
        "medula espinhal_(neuroanatomia)",
        "nervo espinhal",
        "raízes_nervosas",
        "formação_nervosa",
        "MEDICAL_TOPIC",
        ""
      ]
    },
    {
      "question": "Qual é a função do filum terminale?",
      "options": [
        "Transmitir informações do motor",
        "Faça parte da cauda eqüina",
        "Ancorar a medula espinhal caudalmente",
        "Conduzir sinais sensoriais"
      ],
      "correctAnswer": 3,
      "explanation": "O filum terminale é um filamento fibroso que desce do cone medular até o cóccix, servindo como estrutura de ancoragem para manter a medula espinhal em posição.",
      "hashtags": [
        "medula espinhal_(neuroanatomia)",
        "filme_terminale",
        "macro_anatomia",
        "estrutura_âncora",
        "MEDICAL_TOPIC",
        ""
      ]
    }
  ]
}