{
  "id": "acute_myocardial_infarction",
  "items": [
    {
      "order": 0,
      "foco": "Complete",
      "title": "Complete",
      "contentHtml": "<h2>Criterios diagnósticos IAM</h2><h2>Criterios diagnósticos IAM (4ª Definición Universal)</h2><ul><li><b>Diagnóstico:</b> elevación y/o descenso de <b>troponinas</b> (TnI/TnT) con al menos un valor > percentil 99 del límite superior de referencia, más evidencia de isquemia miocárdica aguda.</li><li><b>ECG clave:</b> <b>IAMCEST</b> requiere elevación del ST ≥ 1 mm en derivaciones de extremidades (≥ 2 mm en V2-V3 para hombres < 40 años) o <b>nuevo BRIHH</b>.</li><li><b>Trampa:</b> Elevación de troponinas sin isquemia = <b>daño miocárdico</b> (ej. miocarditis, TEP), no IAM.</li><li><b>Perla:</b> Curva de troponina: ascenso/descenso típico diferencia IAM agudo de crónico.</li></ul><br><br><h2>Clasificación Killip-Kimball</h2><h2>Clasificación de Killip y Kimball (insuficiencia cardíaca en IAM)</h2><ul><li><b>Killip I:</b> Sin signos de IC (mortalidad ~6%).</li><li><b>Killip II:</b> Crepitantes basales, tercer ruido (S3), ingurgitación yugular (mortalidad ~17%).</li><li><b>Killip III:</b> Edema agudo de pulmón (mortalidad ~38%).</li><li><b>Killip IV:</b> Shock cardiogénico (mortalidad >60%).</li><li><b>Examen:</b> Preguntan <b>Killip III vs IV</b>: diferencia es hipotensión y signos de hipoperfusión en IV.</li></ul><br><br><h2>Estratificación TIMI</h2><h2>Estratificación de riesgo TIMI para IAMCEST</h2><ul><li><b>Variables (1 punto c/u):</b> edad ≥ 75 años, DM/HTA/angina, PAS < 100 mmHg, FC > 100 lpm, Killip II-IV, peso < 67 kg, tiempo > 4 h.</li><li><b>Interpretación:</b> Riesgo bajo (0-2 puntos) vs alto (≥ 5 puntos) guía decisión de <b>reperfusión</b>.</li><li><b>Trampa:</b> TIMI para <b>IAMSEST</b> incluye elevación de biomarcadores y uso de AAS, no se usa para decidir fibrinólisis.</li><li><b>Perla:</b> Mortalidad a 30 días: 0.8% (TIMI 0) hasta 35.9% (TIMI 8+).</li></ul><br><br><h2>Reperfusión: ICP vs Fibrinólisis</h2><h2>Terapia de reperfusión en IAMCEST</h2><ul><li><b>Angioplastia primaria (ICP):</b> gold standard si tiempo puerta-balón < 90 min (o < 120 min si traslado).</li><li><b>Fibrinólisis:</b> indicada si ICP no disponible en < 120 min, dentro de <b>12 h</b> de síntomas, sin contraindicaciones (ej. cirugía < 3 sem, ACV hemorrágico previo).</li><li><b>Comparativo:</b> ICP tiene menor riesgo de reinfarto y ACV vs fibrinólisis.</li><li><b>Trampa:</b> Si fibrinólisis fallida (ST < 50% a los 60 min), realizar ICP de rescate.</li></ul><br><br><h2>Antiagregación dual (DAPT)</h2><h2>Indicaciones de DAPT en IAM</h2><ul><li><b>IAMCEST:</b> <b>AAS</b> 300 mg carga, luego 100 mg/día + <b>ticagrelor</b> (180 mg carga, 90 mg c/12 h) o prasugrel (60 mg carga, 10 mg/día).</li><li><b>IAMSEST:</b> AAS + ticagrelor o prasugrel; clopidogrel (600 mg carga) solo si no disponible.</li><li><b>Duración:</b> 12 meses tras IAM (en alto riesgo sangrado, 1-3 meses).</li><li><b>Trampa:</b> Prasugrel contraindicado en ACV/AIT previo; ticagrelor causa disnea reversible.</li></ul><br><br><h2>Complicaciones mecánicas</h2><h2>Complicaciones mecánicas post-IAM</h2><ul><li><b>Rotura de pared libre:</b> taponamiento cardíaco, muerte súbita; pico a los 3-5 días.</li><li><b>Rotura del septo interventricular (CIV):</b> soplo holosistólico + soplo en V2-V3; <b>[Hallazgo clave]:</b> ecocardiograma Doppler color muestra cortocircuito de izquierda a derecha.</li><li><b>Rotura de músculo papilar:</b> insuficiencia mitral aguda, edema pulmonar; soplo apical (puede ser silente si baja presión).</li><li><b>Perla:</b> La <b>trombolisis</b> aumenta riesgo de rotura precoz.</li></ul><br><br><h2>Shock cardiogénico</h2><h2>Manejo del shock cardiogénico en IAM</h2><ul><li><b>Definición:</b> PAS < 90 mmHg + hipoperfusión (extremidades frías, oliguria, alteración mental) tras corrección de volumen.</li><li><b>1ª línea:</b> <b>revascularización urgente</b> (ICP o cirugía); soporte inotrópico con <b>dobutamina</b> o <b>noradrenalina</b> (si PAS < 80 mmHg).</li><li><b>Trampa:</b> Balón de contrapulsación intraaórtico (IABP) no mejora mortalidad en shock (ensayo IABP-SHOCK II).</li><li><b>Perla:</b> ECMO veno-arterial (VA-ECMO) se considera en casos refractarios.</li></ul><br><br><h2>IAM con coronarias normales</h2><h2>Causas de IAM sin obstrucción coronaria significativa (MINOCA)</h2><ul><li><b>Definición:</b> IAM con angiografía coronaria normal (< 50% estenosis).</li><li><b>Causas:</b> <b>espasmo coronario</b> (vasoespasmo), <b>disección coronaria espontánea</b> (especialmente en mujeres jóvenes), <b>embolia coronaria</b> (FA, endocarditis), <b>miocarditis</b> (elevación troponina + realce tardío en RM).</li><li><b>Trampa:</b> Descartar <b>trombosis</b> por trombofilia o síndrome antifosfolípido.</li><li><b>Perla:</b> El diagnóstico diferencial requiere RM cardíaca (realce subendocárdico vs epicárdico).</li></ul><br><br><h2>IAMCEST vs IAMSEST</h2><h2>Diferencias clave IAMCEST vs IAMSEST</h2><ul><li><b>ECG:</b> IAMCEST = elevación ST persistente; IAMSEST = descenso ST o inversión T.</li><li><b>Fisiopatología:</b> IAMCEST suele por oclusión total (trombo rico en fibrina); IAMSEST por oclusión subtotal (trombo rico en plaquetas).</li><li><b>Manejo:</b> IAMCEST requiere reperfusión urgente (ICP/fibrinólisis); IAMSEST se maneja con <b>estrategia invasiva temprana</b> (< 24 h si alto riesgo GRACE).</li><li><b>Biomarcadores:</b> Ambos elevan troponinas; IAMSEST puede tener curva de menor magnitud.</li></ul><br><br><h2>Betabloqueantes agudos</h2><h2>Betabloqueantes en IAM agudo</h2><ul><li><b>Indicación:</b> iniciar vía oral dentro de las primeras 24 h si no hay contraindicaciones (IC, bradicardia, hipotensión, shock).</li><li><b>Beneficio:</b> reducción de mortalidad a largo plazo y riesgo de arritmias.</li><li><b>Contraindicaciones absolutas:</b> <b>Killip III/IV</b>, FC < 60 lpm, PAS < 100 mmHg, bloqueo AV de 2º/3º grado.</li><li><b>Trampa:</b> No usar betabloqueantes intravenosos de rutina en fase aguda (riesgo de shock, estudio COMMIT-CCS-2).</li><li><b>Perla:</b> Preferir <b>metoprolol</b> o <b>carvedilol</b> post-IAM.</li></ul>"
    },
    {
      "order": 1,
      "foco": "Diagnostic criteria for AMI (troponins and ECG)",
      "title": "AMI diagnostic criteria",
      "contentHtml": "<h2>Diagnostic criteria AMI (4th Universal Definition)</h2><ul><li><b>Diagnosis:</b> elevation and/or decrease in <b>troponins</b> (TnI/TnT) with at least a value > 99th percentile of the upper reference limit, plus evidence of acute myocardial ischemia.</li><li><b>Key ECG:</b> <b>STEMI</b> requires ST elevation ≥ 1 mm in extremity leads (≥ 2 mm in V2-V3 for men < 40 years) or <b>new LBBB</b>.</li><li><b>Trap:</b> Elevation of troponins without ischemia = <b>myocardial damage</b> (e.g. myocarditis, PE), not AMI.</li><li><b>Pearl:</b> Troponin curve: Typical rise/fall differentiates acute from chronic AMI. </li></ul>"
    },
    {
      "order": 2,
      "foco": "Killip and Kimball classification",
      "title": "Killip-Kimball classification",
      "contentHtml": "<h2>Killip and Kimball classification (heart failure in AMI)</h2><ul><li><b>Killip I:</b> No signs of HF (mortality ~6%).</li><li><b>Killip II:</b> Basal crackles, third sound (S3), jugular engorgement (mortality ~17%).</li><li><b>Killip III:</b> Acute lung edema (mortality ~38%).</li><li><b>Killip IV:</b> Cardiogenic shock (mortality >60%).</li><li><b>Examination:</b> They ask <b>Killip III vs IV</b>: difference is hypotension and signs of hypoperfusion in IV.</li></ul>"
    },
    {
      "order": 3,
      "foco": "TIMI risk stratification",
      "title": "TIMI stratification",
      "contentHtml": "<h2>TIMI risk stratification for STEMI</h2><ul><li><b>Variables (1 point each):</b> age ≥ 75 years, DM/HTN/angina, SBP < 100 mmHg, HR > 100 bpm, Killip II-IV, weight < 67 kg, time > 4 h.</li><li><b>Interpretation:</b> Low risk (0-2 points) vs high (≥ 5 points) <b>reperfusion</b> decision guide.</li><li><b>Trap:</b> TIMI for <b>NSTEMI</b> includes elevation of biomarkers and use of ASA, not used to decide fibrinolysis.</li><li><b>Pearl:</b> 30-day mortality: 0.8% (TIMI 0) to 35.9% (TIMI 8+).</li></ul>"
    },
    {
      "order": 4,
      "foco": "Reperfusion therapy: primary angioplasty vs fibrinolysis",
      "title": "Reperfusion: PCI vs Fibrinolysis",
      "contentHtml": "<h2>Reperfusion therapy in STEMI</h2><ul><li><b>Primary angioplasty (PCI):</b> gold standard if door-to-balloon time < 90 min (or < 120 min if transfer).</li><li><b>Fibrinolysis:</b> indicated if PCI not available in < 120 min, within <b>12 h</b> of symptoms, without contraindications (e.g. surgery < 3 sem, previous hemorrhagic stroke).</li><li><b>Comparative:</b> PCI has a lower risk of reinfarction and stroke vs fibrinolysis.</li><li><b>Trap:</b> If fibrinolysis fails (ST < 50% at 60 min), perform rescue PCI.</li></ul>"
    },
    {
      "order": 5,
      "foco": "Indications for dual antiplatelet agents",
      "title": "Dual antiaggregation (DAPT)",
      "contentHtml": "<h2>Indications for DAPT in AMI</h2><ul><li><b>STEMI:</b> <b>ASA</b> 300 mg load, then 100 mg/day + <b>ticagrelor</b> (180 mg load, 90 mg every 12 hours) or prasugrel (60 mg load, 10 mg/day).</li><li><b>NSTEMI:</b> ASA + ticagrelor or prasugrel; clopidogrel (600 mg load) only if not available.</li><li><b>Duration:</b> 12 months after AMI (in high bleeding risk, 1-3 months).</li><li><b>Trap:</b> Prasugrel contraindicated in previous stroke/TIA; Ticagrelor causes reversible dyspnea. </li></ul>"
    },
    {
      "order": 6,
      "foco": "Mechanical complications of AMI",
      "title": "Mechanical complications",
      "contentHtml": "<h2>Post-AMI mechanical complications</h2><ul><li><b>Free wall rupture:</b> cardiac tamponade, sudden death; peak at 3-5 days. </li><li><b>Interventricular septal rupture (VSD):</b> holosystolic murmur + murmur in V2-V3; <b>[Key finding]:</b> Color Doppler echocardiogram shows left-to-right shunt.</li><li><b>Papillary muscle rupture:</b> acute mitral regurgitation, pulmonary edema; apical murmur (may be silent if pressure is low).</li><li><b>Pearl:</b> <b>thrombolysis</b> increases the risk of early rupture.</li></ul>"
    },
    {
      "order": 7,
      "foco": "Management of cardiogenic shock",
      "title": "cardiogenic shock",
      "contentHtml": "<h2>Management of cardiogenic shock in AMI</h2><ul><li><b>Definition:</b> SBP < 90 mmHg + hypoperfusion (cold extremities, oliguria, mental alteration) after volume correction.</li><li><b>1st line:</b> <b>urgent revascularization</b> (PCI or surgery); Inotropic support with dobutamine or norepinephrine (if SBP < 80 mmHg). Trap: Intra-aortic balloon pump (IABP) does not improve mortality in shock (IABP-SHOCK II trial). Pearl: Veno-arterial ECMO (VA-ECMO) is considered in cases. refractory. </li></ul>"
    },
    {
      "order": 8,
      "foco": "Causes of AMI with normal coronary arteries",
      "title": "AMI with normal coronary arteries",
      "contentHtml": "<h2>Causes of AMI without significant coronary obstruction (MINOCA)</h2><ul><li><b>Definition:</b> AMI with normal coronary angiography (< 50% stenosis).</li><li><b>Causes:</b> <b>coronary spasm</b> (vasospasm), <b>spontaneous coronary dissection</b> (especially in young women), <b>coronary embolism</b> (AF, endocarditis), myocarditis (troponin elevation + late enhancement on MRI)."
    },
    {
      "order": 9,
      "foco": "Differences between STEMI and NSTEMI",
      "title": "STEMI vs NSTEMI",
      "contentHtml": "<h2>Key differences STEMI vs NSTEMI</h2><ul><li><b>ECG:</b> STEMI = persistent ST elevation; NSTEMI = ST depression or T inversion. </li><li><b>Pathophysiology:</b> STEMI usually due to total occlusion (fibrin-rich thrombus); NSTEMI due to subtotal occlusion (platelet-rich thrombus).</li><li><b>Management:</b> STEMI requires urgent reperfusion (PCI/fibrinolysis); NSTEMI is managed with <b>early invasive strategy</b> (< 24 hours if GRACE high risk).</li><li><b>Biomarkers:</b> Both elevate troponins; NSTEMI may have a curve of smaller magnitude. </li></ul>"
    },
    {
      "order": 10,
      "foco": "Use of beta blockers in the acute phase",
      "title": "Acute beta blockers",
      "contentHtml": "<h2>Beta blockers in acute AMI</h2><ul><li><b>Indication:</b> start orally within the first 24 hours if there are no contraindications (HF, bradycardia, hypotension, shock).</li><li><b>Benefit:</b> reduction of long-term mortality and risk of arrhythmias.</li><li><b>Absolute contraindications:</b> <b>Killip III/IV</b>, HR < 60 bpm, SBP < 100 mmHg, 2nd/3rd degree AV block.</li><li><b>Trap:</b> Do not use routine intravenous beta-blockers in the acute phase (risk of shock, COMMIT-CCS-2 study).</li><li><b>Pearl:</b> Prefer <b>metoprolol</b> or <b>carvedilol</b> post-AMI. </li></ul>"
    }
  ]
}